{"trips": [{"request_time": 0, "start_time": 960, "start_station_id": 0, "end_station_id": 4}, {"request_time": 0, "start_time": 2820, "start_station_id": 9, "end_station_id": 5}, {"request_time": 959, "start_time": 1200, "start_station_id": 9, "end_station_id": 13}, {"request_time": 1332, "start_time": 1620, "start_station_id": 9, "end_station_id": 7}, {"request_time": 0, "start_time": 180, "start_station_id": 9, "end_station_id": 2}, {"request_time": 1682, "start_time": 3420, "start_station_id": 2, "end_station_id": 9}, {"request_time": 0, "start_time": 1080, "start_station_id": 10, "end_station_id": 2}, {"request_time": 739, "start_time": 2160, "start_station_id": 10, "end_station_id": 12}, {"request_time": 1979, "start_time": 2040, "start_station_id": 10, "end_station_id": 7}, {"request_time": 501, "start_time": 2580, "start_station_id": 9, "end_station_id": 0}, {"request_time": 2807, "start_time": 3000, "start_station_id": 1, "end_station_id": 2}, {"request_time": 0, "start_time": 1620, "start_station_id": 7, "end_station_id": 11}, {"request_time": 0, "start_time": 600, "start_station_id": 8, "end_station_id": 9}, {"request_time": 0, "start_time": 2100, "start_station_id": 2, "end_station_id": 9}, {"request_time": 722, "start_time": 2340, "start_station_id": 9, "end_station_id": 13}, {"request_time": 0, "start_time": 1440, "start_station_id": 10, "end_station_id": 12}, {"request_time": 710, "start_time": 1260, "start_station_id": 9, "end_station_id": 7}, {"request_time": 1842, "start_time": 3420, "start_station_id": 13, "end_station_id": 8}, {"request_time": 494, "start_time": 1140, "start_station_id": 6, "end_station_id": 2}, {"request_time": 1867, "start_time": 3300, "start_station_id": 10, "end_station_id": 9}, {"request_time": 0, "start_time": 480, "start_station_id": 5, "end_station_id": 9}, {"request_time": 0, "start_time": 2040, "start_station_id": 9, "end_station_id": 2}, {"request_time": 0, "start_time": 420, "start_station_id": 2, "end_station_id": 6}, {"request_time": 282, "start_time": 3180, "start_station_id": 7, "end_station_id": 5}, {"request_time": 0, "start_time": 840, "start_station_id": 4, "end_station_id": 5}, {"request_time": 0, "start_time": 1320, "start_station_id": 4, "end_station_id": 10}, {"request_time": 0, "start_time": 540, "start_station_id": 9, "end_station_id": 4}, {"request_time": 7, "start_time": 1680, "start_station_id": 5, "end_station_id": 8}, {"request_time": 0, "start_time": 840, "start_station_id": 1, "end_station_id": 7}, {"request_time": 1940, "start_time": 3420, "start_station_id": 13, "end_station_id": 9}, {"request_time": 827, "start_time": 1140, "start_station_id": 3, "end_station_id": 9}, {"request_time": 1073, "start_time": 3000, "start_station_id": 12, "end_station_id": 6}, {"request_time": 266, "start_time": 2400, "start_station_id": 8, "end_station_id": 4}, {"request_time": 0, "start_time": 1080, "start_station_id": 11, "end_station_id": 9}, {"request_time": 0, "start_time": 480, "start_station_id": 9, "end_station_id": 2}, {"request_time": 521, "start_time": 2640, "start_station_id": 9, "end_station_id": 12}, {"request_time": 558, "start_time": 3240, "start_station_id": 8, "end_station_id": 4}, {"request_time": 711, "start_time": 3240, "start_station_id": 3, "end_station_id": 13}, {"request_time": 210, "start_time": 1080, "start_station_id": 9, "end_station_id": 4}, {"request_time": 0, "start_time": 1320, "start_station_id": 4, "end_station_id": 2}, {"request_time": 614, "start_time": 2220, "start_station_id": 3, "end_station_id": 14}, {"request_time": 14, "start_time": 1680, "start_station_id": 9, "end_station_id": 2}, {"request_time": 362, "start_time": 960, "start_station_id": 6, "end_station_id": 5}, {"request_time": 0, "start_time": 780, "start_station_id": 4, "end_station_id": 2}, {"request_time": 1946, "start_time": 2760, "start_station_id": 14, "end_station_id": 4}, {"request_time": 0, "start_time": 2520, "start_station_id": 9, "end_station_id": 11}, {"request_time": 1047, "start_time": 1140, "start_station_id": 5, "end_station_id": 10}, {"request_time": 1372, "start_time": 1380, "start_station_id": 13, "end_station_id": 6}, {"request_time": 339, "start_time": 780, "start_station_id": 9, "end_station_id": 0}, {"request_time": 0, "start_time": 360, "start_station_id": 9, "end_station_id": 8}, {"request_time": 2032, "start_time": 2580, "start_station_id": 7, "end_station_id": 2}, {"request_time": 0, "start_time": 300, "start_station_id": 4, "end_station_id": 12}, {"request_time": 0, "start_time": 900, "start_station_id": 10, "end_station_id": 13}, {"request_time": 0, "start_time": 1860, "start_station_id": 4, "end_station_id": 6}, {"request_time": 0, "start_time": 2100, "start_station_id": 9, "end_station_id": 6}, {"request_time": 0, "start_time": 540, "start_station_id": 12, "end_station_id": 7}, {"request_time": 1273, "start_time": 2700, "start_station_id": 9, "end_station_id": 13}, {"request_time": 1106, "start_time": 2820, "start_station_id": 4, "end_station_id": 8}, {"request_time": 1536, "start_time": 2100, "start_station_id": 9, "end_station_id": 7}, {"request_time": 310, "start_time": 1500, "start_station_id": 9, "end_station_id": 14}, {"request_time": 2909, "start_time": 3360, "start_station_id": 6, "end_station_id": 2}, {"request_time": 1778, "start_time": 3540, "start_station_id": 12, "end_station_id": 7}, {"request_time": 989, "start_time": 3300, "start_station_id": 4, "end_station_id": 10}, {"request_time": 0, "start_time": 2160, "start_station_id": 4, "end_station_id": 2}, {"request_time": 0, "start_time": 300, "start_station_id": 9, "end_station_id": 6}, {"request_time": 0, "start_time": 2040, "start_station_id": 9, "end_station_id": 13}, {"request_time": 0, "start_time": 600, "start_station_id": 9, "end_station_id": 0}, {"request_time": 0, "start_time": 540, "start_station_id": 9, "end_station_id": 10}, {"request_time": 0, "start_time": 3360, "start_station_id": 10, "end_station_id": 6}, {"request_time": 0, "start_time": 480, "start_station_id": 12, "end_station_id": 3}, {"request_time": 3141, "start_time": 3540, "start_station_id": 12, "end_station_id": 14}, {"request_time": 1939, "start_time": 2280, "start_station_id": 3, "end_station_id": 6}, {"request_time": 1766, "start_time": 3480, "start_station_id": 2, "end_station_id": 12}, {"request_time": 0, "start_time": 660, "start_station_id": 2, "end_station_id": 5}, {"request_time": 252, "start_time": 1380, "start_station_id": 8, "end_station_id": 2}, {"request_time": 0, "start_time": 480, "start_station_id": 9, "end_station_id": 3}, {"request_time": 0, "start_time": 840, "start_station_id": 2, "end_station_id": 13}, {"request_time": 0, "start_time": 840, "start_station_id": 10, "end_station_id": 13}, {"request_time": 0, "start_time": 2880, "start_station_id": 2, "end_station_id": 8}, {"request_time": 241, "start_time": 3360, "start_station_id": 14, "end_station_id": 8}, {"request_time": 1495, "start_time": 2940, "start_station_id": 10, "end_station_id": 7}, {"request_time": 2444, "start_time": 3060, "start_station_id": 8, "end_station_id": 9}, {"request_time": 1383, "start_time": 3000, "start_station_id": 8, "end_station_id": 9}, {"request_time": 2339, "start_time": 2400, "start_station_id": 1, "end_station_id": 2}, {"request_time": 625, "start_time": 960, "start_station_id": 14, "end_station_id": 13}, {"request_time": 359, "start_time": 1140, "start_station_id": 6, "end_station_id": 13}, {"request_time": 1243, "start_time": 1560, "start_station_id": 6, "end_station_id": 9}, {"request_time": 754, "start_time": 2880, "start_station_id": 11, "end_station_id": 9}, {"request_time": 0, "start_time": 780, "start_station_id": 9, "end_station_id": 6}, {"request_time": 1940, "start_time": 3240, "start_station_id": 3, "end_station_id": 4}, {"request_time": 0, "start_time": 2940, "start_station_id": 8, "end_station_id": 13}, {"request_time": 919, "start_time": 3360, "start_station_id": 9, "end_station_id": 11}, {"request_time": 0, "start_time": 420, "start_station_id": 6, "end_station_id": 13}, {"request_time": 419, "start_time": 780, "start_station_id": 0, "end_station_id": 4}, {"request_time": 2324, "start_time": 3420, "start_station_id": 9, "end_station_id": 5}, {"request_time": 0, "start_time": 660, "start_station_id": 9, "end_station_id": 13}, {"request_time": 0, "start_time": 2160, "start_station_id": 9, "end_station_id": 7}, {"request_time": 1511, "start_time": 2340, "start_station_id": 9, "end_station_id": 2}, {"request_time": 0, "start_time": 360, "start_station_id": 2, "end_station_id": 9}, {"request_time": 0, "start_time": 960, "start_station_id": 10, "end_station_id": 2}, {"request_time": 0, "start_time": 360, "start_station_id": 10, "end_station_id": 12}, {"request_time": 0, "start_time": 1680, "start_station_id": 10, "end_station_id": 7}, {"request_time": 0, "start_time": 2400, "start_station_id": 9, "end_station_id": 0}, {"request_time": 0, "start_time": 240, "start_station_id": 1, "end_station_id": 2}, {"request_time": 0, "start_time": 1860, "start_station_id": 7, "end_station_id": 11}, {"request_time": 222, "start_time": 900, "start_station_id": 8, "end_station_id": 9}, {"request_time": 232, "start_time": 1440, "start_station_id": 2, "end_station_id": 9}, {"request_time": 0, "start_time": 360, "start_station_id": 9, "end_station_id": 13}, {"request_time": 1176, "start_time": 2100, "start_station_id": 10, "end_station_id": 12}, {"request_time": 1594, "start_time": 2160, "start_station_id": 9, "end_station_id": 7}, {"request_time": 0, "start_time": 120, "start_station_id": 13, "end_station_id": 8}, {"request_time": 1158, "start_time": 1620, "start_station_id": 6, "end_station_id": 2}, {"request_time": 0, "start_time": 2820, "start_station_id": 10, "end_station_id": 9}, {"request_time": 0, "start_time": 600, "start_station_id": 5, "end_station_id": 9}, {"request_time": 0, "start_time": 1260, "start_station_id": 9, "end_station_id": 2}, {"request_time": 0, "start_time": 660, "start_station_id": 2, "end_station_id": 6}, {"request_time": 0, "start_time": 780, "start_station_id": 7, "end_station_id": 5}, {"request_time": 925, "start_time": 1020, "start_station_id": 4, "end_station_id": 5}, {"request_time": 62, "start_time": 2880, "start_station_id": 4, "end_station_id": 10}, {"request_time": 0, "start_time": 1020, "start_station_id": 9, "end_station_id": 4}, {"request_time": 1600, "start_time": 2760, "start_station_id": 5, "end_station_id": 8}, {"request_time": 963, "start_time": 2100, "start_station_id": 1, "end_station_id": 7}, {"request_time": 0, "start_time": 1920, "start_station_id": 13, "end_station_id": 9}, {"request_time": 0, "start_time": 2460, "start_station_id": 3, "end_station_id": 9}, {"request_time": 1838, "start_time": 1860, "start_station_id": 12, "end_station_id": 6}, {"request_time": 443, "start_time": 540, "start_station_id": 8, "end_station_id": 4}, {"request_time": 1459, "start_time": 2100, "start_station_id": 11, "end_station_id": 9}, {"request_time": 1099, "start_time": 2160, "start_station_id": 9, "end_station_id": 2}, {"request_time": 0, "start_time": 240, "start_station_id": 9, "end_station_id": 12}, {"request_time": 467, "start_time": 660, "start_station_id": 8, "end_station_id": 4}, {"request_time": 242, "start_time": 300, "start_station_id": 3, "end_station_id": 13}, {"request_time": 220, "start_time": 3000, "start_station_id": 9, "end_station_id": 4}, {"request_time": 2949, "start_time": 3120, "start_station_id": 4, "end_station_id": 2}, {"request_time": 576, "start_time": 2820, "start_station_id": 9, "end_station_id": 2}, {"request_time": 386, "start_time": 780, "start_station_id": 4, "end_station_id": 2}, {"request_time": 424, "start_time": 1680, "start_station_id": 14, "end_station_id": 4}, {"request_time": 790, "start_time": 1380, "start_station_id": 9, "end_station_id": 11}, {"request_time": 0, "start_time": 840, "start_station_id": 5, "end_station_id": 10}, {"request_time": 0, "start_time": 180, "start_station_id": 13, "end_station_id": 6}, {"request_time": 0, "start_time": 1140, "start_station_id": 9, "end_station_id": 0}, {"request_time": 0, "start_time": 780, "start_station_id": 9, "end_station_id": 8}, {"request_time": 0, "start_time": 840, "start_station_id": 7, "end_station_id": 2}, {"request_time": 0, "start_time": 1440, "start_station_id": 4, "end_station_id": 12}, {"request_time": 1455, "start_time": 1680, "start_station_id": 10, "end_station_id": 13}, {"request_time": 147, "start_time": 3540, "start_station_id": 4, "end_station_id": 6}, {"request_time": 234, "start_time": 3180, "start_station_id": 9, "end_station_id": 6}, {"request_time": 1242, "start_time": 2880, "start_station_id": 12, "end_station_id": 7}, {"request_time": 984, "start_time": 1860, "start_station_id": 9, "end_station_id": 13}, {"request_time": 0, "start_time": 2340, "start_station_id": 4, "end_station_id": 8}, {"request_time": 1186, "start_time": 2940, "start_station_id": 9, "end_station_id": 7}, {"request_time": 759, "start_time": 2880, "start_station_id": 6, "end_station_id": 2}, {"request_time": 0, "start_time": 120, "start_station_id": 12, "end_station_id": 7}, {"request_time": 2046, "start_time": 2940, "start_station_id": 4, "end_station_id": 10}, {"request_time": 91, "start_time": 900, "start_station_id": 4, "end_station_id": 2}, {"request_time": 654, "start_time": 1800, "start_station_id": 9, "end_station_id": 6}, {"request_time": 0, "start_time": 960, "start_station_id": 9, "end_station_id": 13}, {"request_time": 47, "start_time": 1980, "start_station_id": 9, "end_station_id": 0}, {"request_time": 0, "start_time": 420, "start_station_id": 9, "end_station_id": 10}, {"request_time": 432, "start_time": 3300, "start_station_id": 10, "end_station_id": 6}, {"request_time": 0, "start_time": 840, "start_station_id": 12, "end_station_id": 3}, {"request_time": 969, "start_time": 1800, "start_station_id": 12, "end_station_id": 14}, {"request_time": 0, "start_time": 780, "start_station_id": 3, "end_station_id": 6}, {"request_time": 656, "start_time": 3540, "start_station_id": 2, "end_station_id": 12}, {"request_time": 1108, "start_time": 1860, "start_station_id": 2, "end_station_id": 5}, {"request_time": 0, "start_time": 120, "start_station_id": 8, "end_station_id": 2}, {"request_time": 0, "start_time": 420, "start_station_id": 9, "end_station_id": 3}, {"request_time": 0, "start_time": 540, "start_station_id": 2, "end_station_id": 13}, {"request_time": 119, "start_time": 3420, "start_station_id": 10, "end_station_id": 13}, {"request_time": 179, "start_time": 2220, "start_station_id": 2, "end_station_id": 8}, {"request_time": 532, "start_time": 1260, "start_station_id": 14, "end_station_id": 8}, {"request_time": 847, "start_time": 2460, "start_station_id": 10, "end_station_id": 7}, {"request_time": 0, "start_time": 660, "start_station_id": 8, "end_station_id": 9}, {"request_time": 300, "start_time": 2220, "start_station_id": 8, "end_station_id": 9}, {"request_time": 0, "start_time": 1380, "start_station_id": 14, "end_station_id": 9}, {"request_time": 241, "start_time": 1560, "start_station_id": 1, "end_station_id": 2}, {"request_time": 2755, "start_time": 3240, "start_station_id": 14, "end_station_id": 13}, {"request_time": 0, "start_time": 420, "start_station_id": 6, "end_station_id": 13}, {"request_time": 0, "start_time": 300, "start_station_id": 6, "end_station_id": 9}, {"request_time": 0, "start_time": 1500, "start_station_id": 9, "end_station_id": 6}, {"request_time": 0, "start_time": 1500, "start_station_id": 3, "end_station_id": 4}, {"request_time": 28, "start_time": 3420, "start_station_id": 8, "end_station_id": 13}, {"request_time": 821, "start_time": 900, "start_station_id": 9, "end_station_id": 11}]}