[{"request_time": 49548, "start_time": 51300, "start_station_id": 10, "end_station_id": 3}, {"request_time": 41166, "start_time": 41220, "start_station_id": 7, "end_station_id": 5}, {"request_time": 61669, "start_time": 63120, "start_station_id": 0, "end_station_id": 9}, {"request_time": 46447, "start_time": 48540, "start_station_id": 3, "end_station_id": 4}, {"request_time": 6000, "start_time": 6360, "start_station_id": 7, "end_station_id": 2}, {"request_time": 27786, "start_time": 31140, "start_station_id": 9, "end_station_id": 8}, {"request_time": 18862, "start_time": 19020, "start_station_id": 8, "end_station_id": 10}, {"request_time": 24659, "start_time": 28140, "start_station_id": 5, "end_station_id": 7}, {"request_time": 45043, "start_time": 47220, "start_station_id": 0, "end_station_id": 7}, {"request_time": 71810, "start_time": 74700, "start_station_id": 9, "end_station_id": 4}, {"request_time": 49119, "start_time": 52080, "start_station_id": 9, "end_station_id": 2}, {"request_time": 47586, "start_time": 50940, "start_station_id": 9, "end_station_id": 8}, {"request_time": 23533, "start_time": 25980, "start_station_id": 6, "end_station_id": 8}, {"request_time": 79245, "start_time": 80760, "start_station_id": 6, "end_station_id": 13}, {"request_time": 66231, "start_time": 69120, "start_station_id": 4, "end_station_id": 12}, {"request_time": 35546, "start_time": 36480, "start_station_id": 13, "end_station_id": 4}, {"request_time": 63305, "start_time": 66600, "start_station_id": 13, "end_station_id": 9}, {"request_time": 64984, "start_time": 67680, "start_station_id": 14, "end_station_id": 4}, {"request_time": 27934, "start_time": 28500, "start_station_id": 6, "end_station_id": 14}, {"request_time": 1465, "start_time": 4320, "start_station_id": 8, "end_station_id": 4}, {"request_time": 61906, "start_time": 62760, "start_station_id": 2, "end_station_id": 9}, {"request_time": 51221, "start_time": 53760, "start_station_id": 9, "end_station_id": 2}, {"request_time": 36202, "start_time": 36480, "start_station_id": 7, "end_station_id": 9}, {"request_time": 26586, "start_time": 28020, "start_station_id": 9, "end_station_id": 12}, {"request_time": 43931, "start_time": 47040, "start_station_id": 14, "end_station_id": 2}, {"request_time": 16036, "start_time": 18600, "start_station_id": 2, "end_station_id": 8}, {"request_time": 29528, "start_time": 31380, "start_station_id": 0, "end_station_id": 12}, {"request_time": 66837, "start_time": 67260, "start_station_id": 9, "end_station_id": 1}, {"request_time": 13600, "start_time": 13920, "start_station_id": 8, "end_station_id": 7}, {"request_time": 75901, "start_time": 76260, "start_station_id": 9, "end_station_id": 10}, {"request_time": 57268, "start_time": 59520, "start_station_id": 10, "end_station_id": 9}, {"request_time": 43021, "start_time": 45480, "start_station_id": 13, "end_station_id": 10}, {"request_time": 31288, "start_time": 32940, "start_station_id": 12, "end_station_id": 8}, {"request_time": 51660, "start_time": 53520, "start_station_id": 11, "end_station_id": 12}, {"request_time": 33242, "start_time": 34020, "start_station_id": 2, "end_station_id": 1}, {"request_time": 83010, "start_time": 83460, "start_station_id": 13, "end_station_id": 12}, {"request_time": 58279, "start_time": 58800, "start_station_id": 10, "end_station_id": 13}, {"request_time": 64410, "start_time": 66720, "start_station_id": 10, "end_station_id": 9}, {"request_time": 6402, "start_time": 8340, "start_station_id": 9, "end_station_id": 8}, {"request_time": 53623, "start_time": 56940, "start_station_id": 9, "end_station_id": 5}, {"request_time": 31218, "start_time": 32940, "start_station_id": 9, "end_station_id": 2}, {"request_time": 48423, "start_time": 49440, "start_station_id": 9, "end_station_id": 2}, {"request_time": 34378, "start_time": 35520, "start_station_id": 1, "end_station_id": 5}, {"request_time": 25383, "start_time": 26820, "start_station_id": 13, "end_station_id": 14}, {"request_time": 73184, "start_time": 73740, "start_station_id": 9, "end_station_id": 2}, {"request_time": 31154, "start_time": 33960, "start_station_id": 8, "end_station_id": 12}, {"request_time": 15833, "start_time": 17400, "start_station_id": 14, "end_station_id": 12}, {"request_time": 63007, "start_time": 64920, "start_station_id": 7, "end_station_id": 9}, {"request_time": 66241, "start_time": 68220, "start_station_id": 0, "end_station_id": 12}, {"request_time": 38275, "start_time": 38520, "start_station_id": 9, "end_station_id": 13}, {"request_time": 61522, "start_time": 61740, "start_station_id": 0, "end_station_id": 5}, {"request_time": 43279, "start_time": 46860, "start_station_id": 8, "end_station_id": 13}, {"request_time": 65103, "start_time": 68340, "start_station_id": 7, "end_station_id": 0}, {"request_time": 35425, "start_time": 37440, "start_station_id": 13, "end_station_id": 9}, {"request_time": 74758, "start_time": 77400, "start_station_id": 2, "end_station_id": 5}, {"request_time": 82648, "start_time": 82980, "start_station_id": 10, "end_station_id": 3}, {"request_time": 49082, "start_time": 49860, "start_station_id": 7, "end_station_id": 5}, {"request_time": 35679, "start_time": 35700, "start_station_id": 0, "end_station_id": 9}, {"request_time": 61284, "start_time": 64620, "start_station_id": 3, "end_station_id": 4}, {"request_time": 16063, "start_time": 17040, "start_station_id": 7, "end_station_id": 2}, {"request_time": 45111, "start_time": 47460, "start_station_id": 9, "end_station_id": 8}, {"request_time": 23204, "start_time": 26340, "start_station_id": 8, "end_station_id": 10}, {"request_time": 42184, "start_time": 42240, "start_station_id": 5, "end_station_id": 7}, {"request_time": 23946, "start_time": 26580, "start_station_id": 0, "end_station_id": 7}, {"request_time": 10671, "start_time": 14040, "start_station_id": 9, "end_station_id": 4}, {"request_time": 6289, "start_time": 9840, "start_station_id": 9, "end_station_id": 2}, {"request_time": 21012, "start_time": 22020, "start_station_id": 9, "end_station_id": 8}, {"request_time": 73204, "start_time": 73680, "start_station_id": 6, "end_station_id": 8}, {"request_time": 53689, "start_time": 56400, "start_station_id": 6, "end_station_id": 13}, {"request_time": 77188, "start_time": 80040, "start_station_id": 4, "end_station_id": 12}, {"request_time": 46958, "start_time": 47400, "start_station_id": 13, "end_station_id": 4}, {"request_time": 64821, "start_time": 66240, "start_station_id": 13, "end_station_id": 9}, {"request_time": 82472, "start_time": 85920, "start_station_id": 14, "end_station_id": 4}, {"request_time": 51615, "start_time": 53100, "start_station_id": 6, "end_station_id": 14}, {"request_time": 8482, "start_time": 11100, "start_station_id": 8, "end_station_id": 4}, {"request_time": 45730, "start_time": 46560, "start_station_id": 2, "end_station_id": 9}, {"request_time": 38889, "start_time": 39720, "start_station_id": 9, "end_station_id": 2}, {"request_time": 0, "start_time": 2760, "start_station_id": 7, "end_station_id": 9}, {"request_time": 19747, "start_time": 23160, "start_station_id": 9, "end_station_id": 12}, {"request_time": 5199, "start_time": 8640, "start_station_id": 14, "end_station_id": 2}, {"request_time": 47793, "start_time": 49500, "start_station_id": 2, "end_station_id": 8}, {"request_time": 0, "start_time": 420, "start_station_id": 0, "end_station_id": 12}, {"request_time": 12627, "start_time": 14100, "start_station_id": 9, "end_station_id": 1}, {"request_time": 0, "start_time": 1620, "start_station_id": 8, "end_station_id": 7}, {"request_time": 7170, "start_time": 8520, "start_station_id": 9, "end_station_id": 10}, {"request_time": 40531, "start_time": 43740, "start_station_id": 10, "end_station_id": 9}, {"request_time": 42526, "start_time": 45180, "start_station_id": 13, "end_station_id": 10}, {"request_time": 29404, "start_time": 29880, "start_station_id": 12, "end_station_id": 8}, {"request_time": 44794, "start_time": 46320, "start_station_id": 11, "end_station_id": 12}, {"request_time": 64763, "start_time": 66840, "start_station_id": 2, "end_station_id": 1}, {"request_time": 26299, "start_time": 29040, "start_station_id": 13, "end_station_id": 12}, {"request_time": 0, "start_time": 960, "start_station_id": 10, "end_station_id": 13}, {"request_time": 4586, "start_time": 6180, "start_station_id": 10, "end_station_id": 9}, {"request_time": 68448, "start_time": 70020, "start_station_id": 9, "end_station_id": 8}, {"request_time": 43366, "start_time": 44220, "start_station_id": 9, "end_station_id": 5}, {"request_time": 27346, "start_time": 27780, "start_station_id": 9, "end_station_id": 2}, {"request_time": 66871, "start_time": 69900, "start_station_id": 9, "end_station_id": 2}, {"request_time": 48716, "start_time": 49800, "start_station_id": 1, "end_station_id": 5}, {"request_time": 9862, "start_time": 11700, "start_station_id": 13, "end_station_id": 14}, {"request_time": 40233, "start_time": 41880, "start_station_id": 9, "end_station_id": 2}, {"request_time": 66536, "start_time": 68580, "start_station_id": 8, "end_station_id": 12}, {"request_time": 30272, "start_time": 31380, "start_station_id": 14, "end_station_id": 12}, {"request_time": 75416, "start_time": 77040, "start_station_id": 7, "end_station_id": 9}, {"request_time": 16185, "start_time": 16740, "start_station_id": 0, "end_station_id": 12}, {"request_time": 53114, "start_time": 53460, "start_station_id": 9, "end_station_id": 13}, {"request_time": 63071, "start_time": 63780, "start_station_id": 0, "end_station_id": 5}, {"request_time": 75614, "start_time": 78840, "start_station_id": 8, "end_station_id": 13}, {"request_time": 7605, "start_time": 9300, "start_station_id": 7, "end_station_id": 0}, {"request_time": 62002, "start_time": 62280, "start_station_id": 13, "end_station_id": 9}, {"request_time": 84388, "start_time": 85560, "start_station_id": 2, "end_station_id": 5}]