{"trips": [{"request_time": 56045, "start_time": 56640, "start_station_id": 14, "end_station_id": 8}, {"request_time": 83260, "start_time": 84600, "start_station_id": 4, "end_station_id": 0}, {"request_time": 8698, "start_time": 10920, "start_station_id": 6, "end_station_id": 13}, {"request_time": 47732, "start_time": 50520, "start_station_id": 9, "end_station_id": 12}, {"request_time": 36587, "start_time": 37380, "start_station_id": 13, "end_station_id": 9}, {"request_time": 79295, "start_time": 81840, "start_station_id": 4, "end_station_id": 9}, {"request_time": 40876, "start_time": 42780, "start_station_id": 4, "end_station_id": 9}, {"request_time": 31692, "start_time": 34680, "start_station_id": 3, "end_station_id": 2}, {"request_time": 28256, "start_time": 31800, "start_station_id": 9, "end_station_id": 13}, {"request_time": 44211, "start_time": 46020, "start_station_id": 13, "end_station_id": 8}, {"request_time": 3759, "start_time": 7200, "start_station_id": 9, "end_station_id": 8}, {"request_time": 19368, "start_time": 20700, "start_station_id": 6, "end_station_id": 7}, {"request_time": 13476, "start_time": 16500, "start_station_id": 10, "end_station_id": 5}, {"request_time": 26192, "start_time": 27480, "start_station_id": 2, "end_station_id": 0}, {"request_time": 76304, "start_time": 78900, "start_station_id": 6, "end_station_id": 13}, {"request_time": 51811, "start_time": 54300, "start_station_id": 11, "end_station_id": 12}, {"request_time": 19386, "start_time": 19500, "start_station_id": 13, "end_station_id": 2}, {"request_time": 30235, "start_time": 30780, "start_station_id": 9, "end_station_id": 6}, {"request_time": 46803, "start_time": 48540, "start_station_id": 9, "end_station_id": 3}, {"request_time": 6768, "start_time": 7260, "start_station_id": 9, "end_station_id": 12}, {"request_time": 43125, "start_time": 44580, "start_station_id": 8, "end_station_id": 9}, {"request_time": 43824, "start_time": 45000, "start_station_id": 9, "end_station_id": 4}, {"request_time": 83710, "start_time": 85020, "start_station_id": 6, "end_station_id": 5}, {"request_time": 81741, "start_time": 83100, "start_station_id": 7, "end_station_id": 10}, {"request_time": 47151, "start_time": 49380, "start_station_id": 9, "end_station_id": 6}, {"request_time": 51708, "start_time": 53400, "start_station_id": 0, "end_station_id": 9}, {"request_time": 62581, "start_time": 64680, "start_station_id": 4, "end_station_id": 9}, {"request_time": 82657, "start_time": 84180, "start_station_id": 0, "end_station_id": 9}, {"request_time": 24435, "start_time": 26220, "start_station_id": 4, "end_station_id": 10}, {"request_time": 12969, "start_time": 13680, "start_station_id": 9, "end_station_id": 6}, {"request_time": 52214, "start_time": 52620, "start_station_id": 9, "end_station_id": 6}, {"request_time": 52961, "start_time": 53220, "start_station_id": 9, "end_station_id": 2}, {"request_time": 18968, "start_time": 22560, "start_station_id": 9, "end_station_id": 6}, {"request_time": 67483, "start_time": 70860, "start_station_id": 0, "end_station_id": 13}, {"request_time": 55144, "start_time": 56700, "start_station_id": 5, "end_station_id": 9}, {"request_time": 8226, "start_time": 8520, "start_station_id": 6, "end_station_id": 5}, {"request_time": 17901, "start_time": 20760, "start_station_id": 12, "end_station_id": 11}, {"request_time": 6807, "start_time": 7080, "start_station_id": 8, "end_station_id": 2}, {"request_time": 18419, "start_time": 19500, "start_station_id": 3, "end_station_id": 9}, {"request_time": 45842, "start_time": 47880, "start_station_id": 0, "end_station_id": 13}, {"request_time": 16939, "start_time": 17400, "start_station_id": 10, "end_station_id": 8}, {"request_time": 64042, "start_time": 64260, "start_station_id": 8, "end_station_id": 9}, {"request_time": 23999, "start_time": 24660, "start_station_id": 6, "end_station_id": 9}, {"request_time": 24951, "start_time": 27540, "start_station_id": 2, "end_station_id": 6}, {"request_time": 80393, "start_time": 80400, "start_station_id": 3, "end_station_id": 14}, {"request_time": 40635, "start_time": 42840, "start_station_id": 8, "end_station_id": 10}, {"request_time": 1622, "start_time": 2820, "start_station_id": 11, "end_station_id": 10}, {"request_time": 38959, "start_time": 39000, "start_station_id": 6, "end_station_id": 11}, {"request_time": 62941, "start_time": 64560, "start_station_id": 9, "end_station_id": 6}, {"request_time": 61605, "start_time": 64500, "start_station_id": 9, "end_station_id": 3}, {"request_time": 70165, "start_time": 71700, "start_station_id": 2, "end_station_id": 3}, {"request_time": 26457, "start_time": 26640, "start_station_id": 7, "end_station_id": 9}, {"request_time": 82798, "start_time": 83700, "start_station_id": 7, "end_station_id": 8}, {"request_time": 39745, "start_time": 40080, "start_station_id": 0, "end_station_id": 9}, {"request_time": 46523, "start_time": 48240, "start_station_id": 9, "end_station_id": 12}, {"request_time": 29179, "start_time": 30060, "start_station_id": 12, "end_station_id": 13}, {"request_time": 55187, "start_time": 55860, "start_station_id": 12, "end_station_id": 10}, {"request_time": 27753, "start_time": 31320, "start_station_id": 4, "end_station_id": 9}, {"request_time": 43460, "start_time": 45900, "start_station_id": 10, "end_station_id": 9}, {"request_time": 76821, "start_time": 78300, "start_station_id": 3, "end_station_id": 7}, {"request_time": 69958, "start_time": 71580, "start_station_id": 9, "end_station_id": 1}, {"request_time": 56794, "start_time": 60300, "start_station_id": 9, "end_station_id": 10}, {"request_time": 57835, "start_time": 60540, "start_station_id": 9, "end_station_id": 4}, {"request_time": 56955, "start_time": 57720, "start_station_id": 2, "end_station_id": 11}, {"request_time": 36462, "start_time": 36660, "start_station_id": 10, "end_station_id": 9}, {"request_time": 45108, "start_time": 47040, "start_station_id": 11, "end_station_id": 8}, {"request_time": 33126, "start_time": 34680, "start_station_id": 9, "end_station_id": 5}, {"request_time": 46990, "start_time": 50160, "start_station_id": 7, "end_station_id": 6}, {"request_time": 41807, "start_time": 43620, "start_station_id": 0, "end_station_id": 9}, {"request_time": 63679, "start_time": 67080, "start_station_id": 4, "end_station_id": 7}, {"request_time": 23468, "start_time": 23700, "start_station_id": 12, "end_station_id": 1}, {"request_time": 80526, "start_time": 81840, "start_station_id": 13, "end_station_id": 7}, {"request_time": 66841, "start_time": 68280, "start_station_id": 4, "end_station_id": 2}, {"request_time": 74331, "start_time": 76320, "start_station_id": 13, "end_station_id": 14}, {"request_time": 40992, "start_time": 42600, "start_station_id": 9, "end_station_id": 10}, {"request_time": 62910, "start_time": 65280, "start_station_id": 2, "end_station_id": 8}, {"request_time": 10459, "start_time": 13500, "start_station_id": 12, "end_station_id": 1}, {"request_time": 40992, "start_time": 42540, "start_station_id": 12, "end_station_id": 14}, {"request_time": 40824, "start_time": 43920, "start_station_id": 5, "end_station_id": 9}, {"request_time": 69253, "start_time": 72240, "start_station_id": 13, "end_station_id": 5}, {"request_time": 21256, "start_time": 23880, "start_station_id": 2, "end_station_id": 9}, {"request_time": 82494, "start_time": 83640, "start_station_id": 4, "end_station_id": 2}, {"request_time": 39683, "start_time": 42900, "start_station_id": 6, "end_station_id": 10}, {"request_time": 56759, "start_time": 57120, "start_station_id": 6, "end_station_id": 7}, {"request_time": 6505, "start_time": 8460, "start_station_id": 2, "end_station_id": 8}, {"request_time": 49009, "start_time": 49440, "start_station_id": 1, "end_station_id": 13}, {"request_time": 36150, "start_time": 37860, "start_station_id": 9, "end_station_id": 6}, {"request_time": 43127, "start_time": 43800, "start_station_id": 4, "end_station_id": 9}, {"request_time": 23799, "start_time": 24600, "start_station_id": 9, "end_station_id": 1}, {"request_time": 49048, "start_time": 50460, "start_station_id": 13, "end_station_id": 9}, {"request_time": 9374, "start_time": 12480, "start_station_id": 12, "end_station_id": 9}, {"request_time": 26337, "start_time": 27060, "start_station_id": 9, "end_station_id": 2}, {"request_time": 3878, "start_time": 4920, "start_station_id": 8, "end_station_id": 12}, {"request_time": 12452, "start_time": 12720, "start_station_id": 14, "end_station_id": 5}, {"request_time": 44668, "start_time": 44940, "start_station_id": 9, "end_station_id": 7}, {"request_time": 15644, "start_time": 16440, "start_station_id": 13, "end_station_id": 9}, {"request_time": 19946, "start_time": 23040, "start_station_id": 9, "end_station_id": 7}, {"request_time": 6845, "start_time": 8940, "start_station_id": 2, "end_station_id": 12}, {"request_time": 58504, "start_time": 61500, "start_station_id": 6, "end_station_id": 9}, {"request_time": 74201, "start_time": 75540, "start_station_id": 10, "end_station_id": 7}, {"request_time": 80070, "start_time": 80640, "start_station_id": 5, "end_station_id": 13}, {"request_time": 39279, "start_time": 40680, "start_station_id": 7, "end_station_id": 9}, {"request_time": 55711, "start_time": 56340, "start_station_id": 4, "end_station_id": 7}, {"request_time": 50124, "start_time": 51180, "start_station_id": 14, "end_station_id": 0}, {"request_time": 12840, "start_time": 15180, "start_station_id": 6, "end_station_id": 4}, {"request_time": 73803, "start_time": 74220, "start_station_id": 7, "end_station_id": 0}, {"request_time": 60792, "start_time": 63780, "start_station_id": 2, "end_station_id": 13}, {"request_time": 75435, "start_time": 77880, "start_station_id": 2, "end_station_id": 5}, {"request_time": 10663, "start_time": 13560, "start_station_id": 10, "end_station_id": 13}, {"request_time": 24586, "start_time": 26760, "start_station_id": 9, "end_station_id": 11}, {"request_time": 79147, "start_time": 80640, "start_station_id": 9, "end_station_id": 13}, {"request_time": 33228, "start_time": 33720, "start_station_id": 8, "end_station_id": 10}, {"request_time": 1113, "start_time": 3240, "start_station_id": 14, "end_station_id": 10}, {"request_time": 11975, "start_time": 14820, "start_station_id": 6, "end_station_id": 2}, {"request_time": 68228, "start_time": 68640, "start_station_id": 2, "end_station_id": 0}, {"request_time": 10139, "start_time": 12120, "start_station_id": 4, "end_station_id": 13}, {"request_time": 40249, "start_time": 42720, "start_station_id": 9, "end_station_id": 5}, {"request_time": 76507, "start_time": 77880, "start_station_id": 7, "end_station_id": 1}, {"request_time": 31164, "start_time": 34140, "start_station_id": 13, "end_station_id": 14}, {"request_time": 84377, "start_time": 85680, "start_station_id": 4, "end_station_id": 9}, {"request_time": 80919, "start_time": 83640, "start_station_id": 4, "end_station_id": 6}, {"request_time": 38134, "start_time": 40200, "start_station_id": 1, "end_station_id": 3}, {"request_time": 52246, "start_time": 54780, "start_station_id": 10, "end_station_id": 7}, {"request_time": 20924, "start_time": 23400, "start_station_id": 3, "end_station_id": 6}, {"request_time": 1777, "start_time": 4740, "start_station_id": 4, "end_station_id": 7}, {"request_time": 13238, "start_time": 14460, "start_station_id": 6, "end_station_id": 9}, {"request_time": 75582, "start_time": 75600, "start_station_id": 11, "end_station_id": 1}, {"request_time": 36264, "start_time": 38220, "start_station_id": 5, "end_station_id": 13}, {"request_time": 18506, "start_time": 20040, "start_station_id": 11, "end_station_id": 7}, {"request_time": 68009, "start_time": 68220, "start_station_id": 0, "end_station_id": 10}, {"request_time": 72589, "start_time": 75900, "start_station_id": 9, "end_station_id": 10}, {"request_time": 8256, "start_time": 11700, "start_station_id": 7, "end_station_id": 9}, {"request_time": 23486, "start_time": 26340, "start_station_id": 13, "end_station_id": 14}, {"request_time": 74122, "start_time": 75900, "start_station_id": 8, "end_station_id": 9}, {"request_time": 69246, "start_time": 70440, "start_station_id": 7, "end_station_id": 8}, {"request_time": 35478, "start_time": 36780, "start_station_id": 8, "end_station_id": 0}, {"request_time": 3963, "start_time": 6000, "start_station_id": 14, "end_station_id": 10}, {"request_time": 36763, "start_time": 37260, "start_station_id": 0, "end_station_id": 13}, {"request_time": 63257, "start_time": 65700, "start_station_id": 7, "end_station_id": 14}, {"request_time": 73936, "start_time": 76920, "start_station_id": 6, "end_station_id": 14}, {"request_time": 7954, "start_time": 11520, "start_station_id": 10, "end_station_id": 9}, {"request_time": 29602, "start_time": 29940, "start_station_id": 6, "end_station_id": 8}, {"request_time": 58193, "start_time": 58260, "start_station_id": 7, "end_station_id": 5}, {"request_time": 14537, "start_time": 17880, "start_station_id": 5, "end_station_id": 8}, {"request_time": 16581, "start_time": 20160, "start_station_id": 6, "end_station_id": 0}, {"request_time": 40577, "start_time": 43680, "start_station_id": 6, "end_station_id": 13}, {"request_time": 26804, "start_time": 29160, "start_station_id": 9, "end_station_id": 7}, {"request_time": 59784, "start_time": 62880, "start_station_id": 7, "end_station_id": 9}, {"request_time": 10620, "start_time": 10680, "start_station_id": 8, "end_station_id": 2}, {"request_time": 58523, "start_time": 59820, "start_station_id": 4, "end_station_id": 2}, {"request_time": 23906, "start_time": 24780, "start_station_id": 0, "end_station_id": 2}, {"request_time": 26112, "start_time": 26700, "start_station_id": 3, "end_station_id": 1}, {"request_time": 16598, "start_time": 17640, "start_station_id": 12, "end_station_id": 14}, {"request_time": 78297, "start_time": 78540, "start_station_id": 10, "end_station_id": 9}, {"request_time": 35512, "start_time": 37080, "start_station_id": 8, "end_station_id": 1}, {"request_time": 40587, "start_time": 42660, "start_station_id": 7, "end_station_id": 5}, {"request_time": 29161, "start_time": 32280, "start_station_id": 9, "end_station_id": 10}, {"request_time": 45625, "start_time": 47880, "start_station_id": 2, "end_station_id": 8}, {"request_time": 29264, "start_time": 31980, "start_station_id": 13, "end_station_id": 8}, {"request_time": 4757, "start_time": 6180, "start_station_id": 3, "end_station_id": 13}, {"request_time": 57961, "start_time": 59400, "start_station_id": 10, "end_station_id": 0}, {"request_time": 22608, "start_time": 25680, "start_station_id": 5, "end_station_id": 9}, {"request_time": 72848, "start_time": 75060, "start_station_id": 3, "end_station_id": 9}, {"request_time": 64529, "start_time": 66300, "start_station_id": 9, "end_station_id": 3}, {"request_time": 11836, "start_time": 12420, "start_station_id": 5, "end_station_id": 4}, {"request_time": 24177, "start_time": 26520, "start_station_id": 9, "end_station_id": 4}, {"request_time": 70462, "start_time": 72780, "start_station_id": 8, "end_station_id": 12}, {"request_time": 3785, "start_time": 4500, "start_station_id": 13, "end_station_id": 3}, {"request_time": 0, "start_time": 60, "start_station_id": 5, "end_station_id": 9}, {"request_time": 53286, "start_time": 55200, "start_station_id": 7, "end_station_id": 5}, {"request_time": 2463, "start_time": 4920, "start_station_id": 4, "end_station_id": 9}, {"request_time": 53196, "start_time": 53520, "start_station_id": 4, "end_station_id": 12}, {"request_time": 5811, "start_time": 7920, "start_station_id": 4, "end_station_id": 2}, {"request_time": 30311, "start_time": 30360, "start_station_id": 5, "end_station_id": 8}, {"request_time": 17086, "start_time": 19500, "start_station_id": 9, "end_station_id": 7}, {"request_time": 2992, "start_time": 4020, "start_station_id": 9, "end_station_id": 3}, {"request_time": 9686, "start_time": 10980, "start_station_id": 3, "end_station_id": 5}, {"request_time": 53918, "start_time": 56700, "start_station_id": 9, "end_station_id": 13}, {"request_time": 82239, "start_time": 85380, "start_station_id": 13, "end_station_id": 9}, {"request_time": 33139, "start_time": 34320, "start_station_id": 2, "end_station_id": 9}, {"request_time": 81290, "start_time": 81540, "start_station_id": 7, "end_station_id": 3}, {"request_time": 64452, "start_time": 67140, "start_station_id": 3, "end_station_id": 13}, {"request_time": 59257, "start_time": 61860, "start_station_id": 5, "end_station_id": 2}, {"request_time": 71332, "start_time": 72960, "start_station_id": 14, "end_station_id": 9}, {"request_time": 25565, "start_time": 26640, "start_station_id": 9, "end_station_id": 7}, {"request_time": 1364, "start_time": 3900, "start_station_id": 9, "end_station_id": 8}, {"request_time": 68879, "start_time": 68940, "start_station_id": 10, "end_station_id": 9}, {"request_time": 62413, "start_time": 66000, "start_station_id": 8, "end_station_id": 9}, {"request_time": 17154, "start_time": 19920, "start_station_id": 8, "end_station_id": 7}, {"request_time": 54246, "start_time": 54900, "start_station_id": 4, "end_station_id": 11}, {"request_time": 55118, "start_time": 55620, "start_station_id": 3, "end_station_id": 2}, {"request_time": 44456, "start_time": 47220, "start_station_id": 9, "end_station_id": 5}, {"request_time": 11362, "start_time": 13920, "start_station_id": 10, "end_station_id": 9}, {"request_time": 73763, "start_time": 75120, "start_station_id": 2, "end_station_id": 3}, {"request_time": 81912, "start_time": 83700, "start_station_id": 9, "end_station_id": 8}, {"request_time": 25381, "start_time": 25800, "start_station_id": 5, "end_station_id": 12}, {"request_time": 48518, "start_time": 51300, "start_station_id": 13, "end_station_id": 5}, {"request_time": 63701, "start_time": 66540, "start_station_id": 6, "end_station_id": 9}, {"request_time": 76893, "start_time": 79440, "start_station_id": 6, "end_station_id": 9}, {"request_time": 17587, "start_time": 18540, "start_station_id": 9, "end_station_id": 11}, {"request_time": 81043, "start_time": 84240, "start_station_id": 9, "end_station_id": 7}, {"request_time": 65177, "start_time": 65460, "start_station_id": 10, "end_station_id": 14}, {"request_time": 72399, "start_time": 72540, "start_station_id": 3, "end_station_id": 6}, {"request_time": 76838, "start_time": 80220, "start_station_id": 10, "end_station_id": 13}, {"request_time": 60709, "start_time": 61800, "start_station_id": 4, "end_station_id": 10}, {"request_time": 8478, "start_time": 11160, "start_station_id": 2, "end_station_id": 12}, {"request_time": 82358, "start_time": 82560, "start_station_id": 1, "end_station_id": 9}, {"request_time": 21928, "start_time": 22020, "start_station_id": 4, "end_station_id": 9}, {"request_time": 77496, "start_time": 78180, "start_station_id": 4, "end_station_id": 9}, {"request_time": 16876, "start_time": 19260, "start_station_id": 9, "end_station_id": 0}, {"request_time": 6092, "start_time": 7920, "start_station_id": 11, "end_station_id": 6}, {"request_time": 66008, "start_time": 66600, "start_station_id": 7, "end_station_id": 6}, {"request_time": 73898, "start_time": 75060, "start_station_id": 2, "end_station_id": 9}, {"request_time": 73787, "start_time": 74580, "start_station_id": 12, "end_station_id": 5}, {"request_time": 22417, "start_time": 23040, "start_station_id": 11, "end_station_id": 13}, {"request_time": 25307, "start_time": 26400, "start_station_id": 4, "end_station_id": 9}, {"request_time": 66421, "start_time": 68700, "start_station_id": 6, "end_station_id": 9}, {"request_time": 25912, "start_time": 27060, "start_station_id": 9, "end_station_id": 4}, {"request_time": 1731, "start_time": 3360, "start_station_id": 10, "end_station_id": 12}, {"request_time": 22721, "start_time": 24480, "start_station_id": 3, "end_station_id": 14}, {"request_time": 27400, "start_time": 29820, "start_station_id": 13, "end_station_id": 7}, {"request_time": 62063, "start_time": 62820, "start_station_id": 9, "end_station_id": 7}, {"request_time": 52827, "start_time": 55680, "start_station_id": 12, "end_station_id": 6}, {"request_time": 13872, "start_time": 14040, "start_station_id": 12, "end_station_id": 3}, {"request_time": 61431, "start_time": 63060, "start_station_id": 14, "end_station_id": 8}, {"request_time": 22418, "start_time": 23280, "start_station_id": 4, "end_station_id": 0}, {"request_time": 0, "start_time": 2580, "start_station_id": 6, "end_station_id": 13}, {"request_time": 3337, "start_time": 6360, "start_station_id": 9, "end_station_id": 12}, {"request_time": 67564, "start_time": 71040, "start_station_id": 13, "end_station_id": 9}, {"request_time": 55396, "start_time": 58320, "start_station_id": 4, "end_station_id": 9}, {"request_time": 44841, "start_time": 46560, "start_station_id": 4, "end_station_id": 9}, {"request_time": 74158, "start_time": 77220, "start_station_id": 3, "end_station_id": 2}, {"request_time": 27268, "start_time": 27540, "start_station_id": 9, "end_station_id": 13}, {"request_time": 76568, "start_time": 78420, "start_station_id": 13, "end_station_id": 8}, {"request_time": 63971, "start_time": 67320, "start_station_id": 9, "end_station_id": 8}, {"request_time": 80532, "start_time": 81540, "start_station_id": 6, "end_station_id": 7}, {"request_time": 20438, "start_time": 23820, "start_station_id": 10, "end_station_id": 5}, {"request_time": 56588, "start_time": 59820, "start_station_id": 2, "end_station_id": 0}, {"request_time": 65446, "start_time": 68220, "start_station_id": 6, "end_station_id": 13}, {"request_time": 47554, "start_time": 49860, "start_station_id": 11, "end_station_id": 12}, {"request_time": 47874, "start_time": 49560, "start_station_id": 13, "end_station_id": 2}, {"request_time": 25637, "start_time": 27660, "start_station_id": 9, "end_station_id": 6}, {"request_time": 80358, "start_time": 81420, "start_station_id": 9, "end_station_id": 3}, {"request_time": 84292, "start_time": 84840, "start_station_id": 9, "end_station_id": 12}, {"request_time": 23311, "start_time": 25080, "start_station_id": 8, "end_station_id": 9}, {"request_time": 79800, "start_time": 81060, "start_station_id": 9, "end_station_id": 4}, {"request_time": 24912, "start_time": 26100, "start_station_id": 6, "end_station_id": 5}, {"request_time": 72666, "start_time": 72840, "start_station_id": 7, "end_station_id": 10}, {"request_time": 42761, "start_time": 46260, "start_station_id": 9, "end_station_id": 6}, {"request_time": 73778, "start_time": 76800, "start_station_id": 0, "end_station_id": 9}, {"request_time": 32353, "start_time": 35940, "start_station_id": 4, "end_station_id": 9}, {"request_time": 79858, "start_time": 80220, "start_station_id": 0, "end_station_id": 9}, {"request_time": 0, "start_time": 1260, "start_station_id": 4, "end_station_id": 10}, {"request_time": 19870, "start_time": 22320, "start_station_id": 9, "end_station_id": 6}, {"request_time": 48950, "start_time": 49860, "start_station_id": 9, "end_station_id": 6}, {"request_time": 21858, "start_time": 24540, "start_station_id": 9, "end_station_id": 2}, {"request_time": 62057, "start_time": 65640, "start_station_id": 9, "end_station_id": 6}, {"request_time": 56692, "start_time": 60120, "start_station_id": 0, "end_station_id": 13}, {"request_time": 58334, "start_time": 58380, "start_station_id": 5, "end_station_id": 9}, {"request_time": 57945, "start_time": 59880, "start_station_id": 6, "end_station_id": 5}, {"request_time": 85812, "start_time": 86100, "start_station_id": 12, "end_station_id": 11}, {"request_time": 8926, "start_time": 9780, "start_station_id": 8, "end_station_id": 2}, {"request_time": 32581, "start_time": 35460, "start_station_id": 3, "end_station_id": 9}, {"request_time": 74109, "start_time": 77520, "start_station_id": 0, "end_station_id": 13}, {"request_time": 10748, "start_time": 14220, "start_station_id": 10, "end_station_id": 8}, {"request_time": 19007, "start_time": 22440, "start_station_id": 8, "end_station_id": 9}, {"request_time": 9632, "start_time": 10140, "start_station_id": 6, "end_station_id": 9}, {"request_time": 64215, "start_time": 67380, "start_station_id": 2, "end_station_id": 6}, {"request_time": 31514, "start_time": 32880, "start_station_id": 3, "end_station_id": 14}, {"request_time": 64597, "start_time": 64620, "start_station_id": 8, "end_station_id": 10}, {"request_time": 62951, "start_time": 66060, "start_station_id": 11, "end_station_id": 10}, {"request_time": 39071, "start_time": 42300, "start_station_id": 6, "end_station_id": 11}, {"request_time": 1021, "start_time": 1740, "start_station_id": 9, "end_station_id": 6}, {"request_time": 9554, "start_time": 11820, "start_station_id": 9, "end_station_id": 3}, {"request_time": 15057, "start_time": 18600, "start_station_id": 2, "end_station_id": 3}, {"request_time": 68817, "start_time": 69000, "start_station_id": 7, "end_station_id": 9}, {"request_time": 40783, "start_time": 44220, "start_station_id": 7, "end_station_id": 8}, {"request_time": 41758, "start_time": 43320, "start_station_id": 0, "end_station_id": 9}, {"request_time": 79484, "start_time": 80700, "start_station_id": 9, "end_station_id": 12}, {"request_time": 23186, "start_time": 24900, "start_station_id": 12, "end_station_id": 13}, {"request_time": 36768, "start_time": 40140, "start_station_id": 12, "end_station_id": 10}, {"request_time": 50051, "start_time": 50340, "start_station_id": 4, "end_station_id": 9}, {"request_time": 69142, "start_time": 69660, "start_station_id": 10, "end_station_id": 9}, {"request_time": 72013, "start_time": 72300, "start_station_id": 3, "end_station_id": 7}, {"request_time": 13372, "start_time": 13920, "start_station_id": 9, "end_station_id": 1}, {"request_time": 46795, "start_time": 49680, "start_station_id": 9, "end_station_id": 10}, {"request_time": 64869, "start_time": 65640, "start_station_id": 9, "end_station_id": 4}, {"request_time": 0, "start_time": 1320, "start_station_id": 2, "end_station_id": 11}, {"request_time": 15547, "start_time": 16320, "start_station_id": 10, "end_station_id": 9}, {"request_time": 35370, "start_time": 36360, "start_station_id": 11, "end_station_id": 8}, {"request_time": 2129, "start_time": 5520, "start_station_id": 9, "end_station_id": 5}, {"request_time": 21071, "start_time": 21960, "start_station_id": 7, "end_station_id": 6}, {"request_time": 57110, "start_time": 57540, "start_station_id": 0, "end_station_id": 9}, {"request_time": 81298, "start_time": 82920, "start_station_id": 4, "end_station_id": 7}, {"request_time": 58211, "start_time": 61500, "start_station_id": 12, "end_station_id": 1}, {"request_time": 5450, "start_time": 7800, "start_station_id": 13, "end_station_id": 7}, {"request_time": 35765, "start_time": 38580, "start_station_id": 4, "end_station_id": 2}, {"request_time": 25543, "start_time": 28440, "start_station_id": 13, "end_station_id": 14}, {"request_time": 0, "start_time": 240, "start_station_id": 9, "end_station_id": 10}, {"request_time": 31290, "start_time": 31440, "start_station_id": 2, "end_station_id": 8}, {"request_time": 10505, "start_time": 13980, "start_station_id": 12, "end_station_id": 1}, {"request_time": 70710, "start_time": 73740, "start_station_id": 12, "end_station_id": 14}, {"request_time": 33648, "start_time": 35700, "start_station_id": 5, "end_station_id": 9}, {"request_time": 868, "start_time": 1500, "start_station_id": 13, "end_station_id": 5}, {"request_time": 25181, "start_time": 25860, "start_station_id": 2, "end_station_id": 9}, {"request_time": 57441, "start_time": 58740, "start_station_id": 4, "end_station_id": 2}, {"request_time": 41853, "start_time": 45420, "start_station_id": 6, "end_station_id": 10}, {"request_time": 29740, "start_time": 29940, "start_station_id": 6, "end_station_id": 7}, {"request_time": 68416, "start_time": 70800, "start_station_id": 2, "end_station_id": 8}, {"request_time": 39441, "start_time": 40560, "start_station_id": 1, "end_station_id": 13}, {"request_time": 37039, "start_time": 37680, "start_station_id": 9, "end_station_id": 6}, {"request_time": 74804, "start_time": 76140, "start_station_id": 4, "end_station_id": 9}, {"request_time": 23824, "start_time": 27300, "start_station_id": 9, "end_station_id": 1}, {"request_time": 46289, "start_time": 49620, "start_station_id": 13, "end_station_id": 9}, {"request_time": 73467, "start_time": 74700, "start_station_id": 12, "end_station_id": 9}, {"request_time": 3176, "start_time": 4320, "start_station_id": 9, "end_station_id": 2}, {"request_time": 12174, "start_time": 13560, "start_station_id": 8, "end_station_id": 12}, {"request_time": 50238, "start_time": 51360, "start_station_id": 14, "end_station_id": 5}, {"request_time": 39054, "start_time": 41700, "start_station_id": 9, "end_station_id": 7}, {"request_time": 72538, "start_time": 74040, "start_station_id": 13, "end_station_id": 9}, {"request_time": 8276, "start_time": 11040, "start_station_id": 9, "end_station_id": 7}, {"request_time": 83164, "start_time": 86160, "start_station_id": 2, "end_station_id": 12}, {"request_time": 10699, "start_time": 13440, "start_station_id": 6, "end_station_id": 9}, {"request_time": 4407, "start_time": 7620, "start_station_id": 10, "end_station_id": 7}, {"request_time": 29237, "start_time": 31680, "start_station_id": 5, "end_station_id": 13}, {"request_time": 66783, "start_time": 70080, "start_station_id": 7, "end_station_id": 9}, {"request_time": 61940, "start_time": 63000, "start_station_id": 4, "end_station_id": 7}, {"request_time": 927, "start_time": 3600, "start_station_id": 14, "end_station_id": 0}, {"request_time": 57856, "start_time": 60840, "start_station_id": 6, "end_station_id": 4}, {"request_time": 10510, "start_time": 13980, "start_station_id": 7, "end_station_id": 0}, {"request_time": 58606, "start_time": 60960, "start_station_id": 2, "end_station_id": 13}, {"request_time": 2289, "start_time": 2940, "start_station_id": 2, "end_station_id": 5}, {"request_time": 24999, "start_time": 28200, "start_station_id": 10, "end_station_id": 13}, {"request_time": 9126, "start_time": 12180, "start_station_id": 9, "end_station_id": 11}, {"request_time": 41004, "start_time": 44400, "start_station_id": 9, "end_station_id": 13}, {"request_time": 80501, "start_time": 84000, "start_station_id": 8, "end_station_id": 10}, {"request_time": 6435, "start_time": 8220, "start_station_id": 14, "end_station_id": 10}, {"request_time": 15076, "start_time": 15540, "start_station_id": 6, "end_station_id": 2}, {"request_time": 52304, "start_time": 54540, "start_station_id": 2, "end_station_id": 0}, {"request_time": 36712, "start_time": 37380, "start_station_id": 4, "end_station_id": 13}, {"request_time": 42742, "start_time": 45180, "start_station_id": 9, "end_station_id": 5}, {"request_time": 23129, "start_time": 24900, "start_station_id": 7, "end_station_id": 1}, {"request_time": 65656, "start_time": 65820, "start_station_id": 13, "end_station_id": 14}, {"request_time": 28133, "start_time": 31680, "start_station_id": 4, "end_station_id": 9}, {"request_time": 51084, "start_time": 53820, "start_station_id": 4, "end_station_id": 6}, {"request_time": 77766, "start_time": 79080, "start_station_id": 1, "end_station_id": 3}, {"request_time": 32072, "start_time": 35100, "start_station_id": 10, "end_station_id": 7}, {"request_time": 43283, "start_time": 46140, "start_station_id": 3, "end_station_id": 6}, {"request_time": 73915, "start_time": 75240, "start_station_id": 4, "end_station_id": 7}, {"request_time": 42637, "start_time": 44340, "start_station_id": 6, "end_station_id": 9}, {"request_time": 17700, "start_time": 21060, "start_station_id": 11, "end_station_id": 1}, {"request_time": 15575, "start_time": 16080, "start_station_id": 5, "end_station_id": 13}, {"request_time": 82058, "start_time": 82680, "start_station_id": 11, "end_station_id": 7}, {"request_time": 53700, "start_time": 53820, "start_station_id": 0, "end_station_id": 10}, {"request_time": 49961, "start_time": 50280, "start_station_id": 9, "end_station_id": 10}, {"request_time": 84321, "start_time": 85500, "start_station_id": 7, "end_station_id": 9}, {"request_time": 22349, "start_time": 23280, "start_station_id": 13, "end_station_id": 14}, {"request_time": 42229, "start_time": 42960, "start_station_id": 8, "end_station_id": 9}, {"request_time": 16192, "start_time": 19680, "start_station_id": 7, "end_station_id": 8}, {"request_time": 25871, "start_time": 28980, "start_station_id": 8, "end_station_id": 0}, {"request_time": 13212, "start_time": 13560, "start_station_id": 14, "end_station_id": 10}, {"request_time": 2540, "start_time": 3600, "start_station_id": 0, "end_station_id": 13}, {"request_time": 51438, "start_time": 53400, "start_station_id": 7, "end_station_id": 14}, {"request_time": 70443, "start_time": 73140, "start_station_id": 6, "end_station_id": 14}, {"request_time": 9038, "start_time": 11460, "start_station_id": 10, "end_station_id": 9}, {"request_time": 66136, "start_time": 68220, "start_station_id": 6, "end_station_id": 8}, {"request_time": 9280, "start_time": 11940, "start_station_id": 7, "end_station_id": 5}, {"request_time": 21020, "start_time": 23580, "start_station_id": 5, "end_station_id": 8}, {"request_time": 66203, "start_time": 66420, "start_station_id": 6, "end_station_id": 0}, {"request_time": 11953, "start_time": 12180, "start_station_id": 6, "end_station_id": 13}, {"request_time": 49747, "start_time": 51120, "start_station_id": 9, "end_station_id": 7}, {"request_time": 66741, "start_time": 68100, "start_station_id": 7, "end_station_id": 9}, {"request_time": 64247, "start_time": 66300, "start_station_id": 8, "end_station_id": 2}, {"request_time": 10874, "start_time": 14040, "start_station_id": 4, "end_station_id": 2}, {"request_time": 31515, "start_time": 34380, "start_station_id": 0, "end_station_id": 2}, {"request_time": 82775, "start_time": 84360, "start_station_id": 3, "end_station_id": 1}, {"request_time": 58566, "start_time": 61500, "start_station_id": 12, "end_station_id": 14}, {"request_time": 20465, "start_time": 21900, "start_station_id": 10, "end_station_id": 9}, {"request_time": 33465, "start_time": 36120, "start_station_id": 8, "end_station_id": 1}, {"request_time": 81145, "start_time": 81660, "start_station_id": 7, "end_station_id": 5}, {"request_time": 32750, "start_time": 34080, "start_station_id": 9, "end_station_id": 10}, {"request_time": 37046, "start_time": 39000, "start_station_id": 2, "end_station_id": 8}, {"request_time": 62651, "start_time": 62880, "start_station_id": 13, "end_station_id": 8}, {"request_time": 66681, "start_time": 66960, "start_station_id": 3, "end_station_id": 13}, {"request_time": 23755, "start_time": 26460, "start_station_id": 10, "end_station_id": 0}, {"request_time": 61608, "start_time": 63960, "start_station_id": 5, "end_station_id": 9}, {"request_time": 66902, "start_time": 69300, "start_station_id": 3, "end_station_id": 9}, {"request_time": 59324, "start_time": 61920, "start_station_id": 9, "end_station_id": 3}, {"request_time": 53685, "start_time": 56820, "start_station_id": 5, "end_station_id": 4}, {"request_time": 22061, "start_time": 23400, "start_station_id": 9, "end_station_id": 4}, {"request_time": 65504, "start_time": 67800, "start_station_id": 8, "end_station_id": 12}, {"request_time": 41656, "start_time": 42600, "start_station_id": 13, "end_station_id": 3}, {"request_time": 74121, "start_time": 75600, "start_station_id": 5, "end_station_id": 9}, {"request_time": 13999, "start_time": 14100, "start_station_id": 7, "end_station_id": 5}, {"request_time": 78429, "start_time": 79080, "start_station_id": 4, "end_station_id": 9}, {"request_time": 13869, "start_time": 14400, "start_station_id": 4, "end_station_id": 12}, {"request_time": 19241, "start_time": 20880, "start_station_id": 4, "end_station_id": 2}, {"request_time": 49990, "start_time": 53520, "start_station_id": 5, "end_station_id": 8}, {"request_time": 43005, "start_time": 44880, "start_station_id": 9, "end_station_id": 7}, {"request_time": 58967, "start_time": 61920, "start_station_id": 9, "end_station_id": 3}, {"request_time": 9680, "start_time": 12120, "start_station_id": 3, "end_station_id": 5}, {"request_time": 66908, "start_time": 66960, "start_station_id": 9, "end_station_id": 13}, {"request_time": 71328, "start_time": 71340, "start_station_id": 13, "end_station_id": 9}, {"request_time": 70093, "start_time": 72480, "start_station_id": 2, "end_station_id": 9}, {"request_time": 65271, "start_time": 67380, "start_station_id": 7, "end_station_id": 3}, {"request_time": 46110, "start_time": 47820, "start_station_id": 3, "end_station_id": 13}, {"request_time": 37373, "start_time": 38340, "start_station_id": 5, "end_station_id": 2}, {"request_time": 48332, "start_time": 51360, "start_station_id": 14, "end_station_id": 9}, {"request_time": 22753, "start_time": 24540, "start_station_id": 9, "end_station_id": 7}, {"request_time": 80755, "start_time": 82920, "start_station_id": 9, "end_station_id": 8}, {"request_time": 80917, "start_time": 82980, "start_station_id": 10, "end_station_id": 9}, {"request_time": 60775, "start_time": 64320, "start_station_id": 8, "end_station_id": 9}, {"request_time": 62903, "start_time": 63240, "start_station_id": 8, "end_station_id": 7}, {"request_time": 74921, "start_time": 76980, "start_station_id": 4, "end_station_id": 11}, {"request_time": 83092, "start_time": 84300, "start_station_id": 3, "end_station_id": 2}, {"request_time": 66953, "start_time": 68340, "start_station_id": 9, "end_station_id": 5}, {"request_time": 63809, "start_time": 65100, "start_station_id": 10, "end_station_id": 9}, {"request_time": 76904, "start_time": 79020, "start_station_id": 2, "end_station_id": 3}, {"request_time": 50710, "start_time": 52080, "start_station_id": 9, "end_station_id": 8}, {"request_time": 45395, "start_time": 48720, "start_station_id": 5, "end_station_id": 12}, {"request_time": 61324, "start_time": 63660, "start_station_id": 13, "end_station_id": 5}, {"request_time": 43056, "start_time": 46200, "start_station_id": 6, "end_station_id": 9}, {"request_time": 75259, "start_time": 78000, "start_station_id": 6, "end_station_id": 9}, {"request_time": 42459, "start_time": 44460, "start_station_id": 9, "end_station_id": 11}, {"request_time": 26732, "start_time": 26940, "start_station_id": 9, "end_station_id": 7}, {"request_time": 5888, "start_time": 8580, "start_station_id": 10, "end_station_id": 14}, {"request_time": 26961, "start_time": 28680, "start_station_id": 3, "end_station_id": 6}, {"request_time": 37037, "start_time": 38880, "start_station_id": 10, "end_station_id": 13}, {"request_time": 4119, "start_time": 7560, "start_station_id": 4, "end_station_id": 10}, {"request_time": 23356, "start_time": 26820, "start_station_id": 2, "end_station_id": 12}, {"request_time": 19087, "start_time": 20160, "start_station_id": 1, "end_station_id": 9}, {"request_time": 36014, "start_time": 38280, "start_station_id": 4, "end_station_id": 9}, {"request_time": 45839, "start_time": 47640, "start_station_id": 4, "end_station_id": 9}, {"request_time": 85243, "start_time": 86220, "start_station_id": 9, "end_station_id": 0}, {"request_time": 43198, "start_time": 43680, "start_station_id": 11, "end_station_id": 6}, {"request_time": 84953, "start_time": 85320, "start_station_id": 7, "end_station_id": 6}, {"request_time": 59806, "start_time": 61080, "start_station_id": 2, "end_station_id": 9}, {"request_time": 19432, "start_time": 22200, "start_station_id": 12, "end_station_id": 5}, {"request_time": 46466, "start_time": 48480, "start_station_id": 11, "end_station_id": 13}, {"request_time": 39079, "start_time": 39240, "start_station_id": 4, "end_station_id": 9}, {"request_time": 83592, "start_time": 84720, "start_station_id": 6, "end_station_id": 9}, {"request_time": 16887, "start_time": 20160, "start_station_id": 9, "end_station_id": 4}, {"request_time": 32982, "start_time": 33180, "start_station_id": 10, "end_station_id": 12}, {"request_time": 23093, "start_time": 25740, "start_station_id": 3, "end_station_id": 14}, {"request_time": 83716, "start_time": 83880, "start_station_id": 13, "end_station_id": 7}, {"request_time": 23322, "start_time": 24780, "start_station_id": 9, "end_station_id": 7}, {"request_time": 73117, "start_time": 73980, "start_station_id": 12, "end_station_id": 6}, {"request_time": 51801, "start_time": 51840, "start_station_id": 12, "end_station_id": 3}]}