{"trips": [{"request_time": 0, "start_time": 20700, "start_station_id": 13, "end_station_id": 2}, {"request_time": 0, "start_time": 41640, "start_station_id": 8, "end_station_id": 10}, {"request_time": 0, "start_time": 16440, "start_station_id": 11, "end_station_id": 12}, {"request_time": 0, "start_time": 68280, "start_station_id": 11, "end_station_id": 8}, {"request_time": 0, "start_time": 49440, "start_station_id": 13, "end_station_id": 10}, {"request_time": 0, "start_time": 15060, "start_station_id": 5, "end_station_id": 9}, {"request_time": 0, "start_time": 67320, "start_station_id": 10, "end_station_id": 1}, {"request_time": 0, "start_time": 56460, "start_station_id": 4, "end_station_id": 6}, {"request_time": 0, "start_time": 72720, "start_station_id": 9, "end_station_id": 14}, {"request_time": 0, "start_time": 28980, "start_station_id": 4, "end_station_id": 6}, {"request_time": 0, "start_time": 76680, "start_station_id": 4, "end_station_id": 0}, {"request_time": 0, "start_time": 33060, "start_station_id": 8, "end_station_id": 9}, {"request_time": 0, "start_time": 12960, "start_station_id": 5, "end_station_id": 2}, {"request_time": 0, "start_time": 25260, "start_station_id": 6, "end_station_id": 9}, {"request_time": 0, "start_time": 60660, "start_station_id": 5, "end_station_id": 12}, {"request_time": 0, "start_time": 44400, "start_station_id": 13, "end_station_id": 6}, {"request_time": 0, "start_time": 16740, "start_station_id": 10, "end_station_id": 8}, {"request_time": 0, "start_time": 6720, "start_station_id": 13, "end_station_id": 6}, {"request_time": 0, "start_time": 86100, "start_station_id": 13, "end_station_id": 9}, {"request_time": 0, "start_time": 51420, "start_station_id": 12, "end_station_id": 13}, {"request_time": 0, "start_time": 11220, "start_station_id": 6, "end_station_id": 8}, {"request_time": 0, "start_time": 85440, "start_station_id": 11, "end_station_id": 9}, {"request_time": 0, "start_time": 77640, "start_station_id": 4, "end_station_id": 2}, {"request_time": 0, "start_time": 19800, "start_station_id": 1, "end_station_id": 7}, {"request_time": 0, "start_time": 45300, "start_station_id": 10, "end_station_id": 9}, {"request_time": 0, "start_time": 78480, "start_station_id": 9, "end_station_id": 1}, {"request_time": 0, "start_time": 51420, "start_station_id": 6, "end_station_id": 0}, {"request_time": 0, "start_time": 83040, "start_station_id": 10, "end_station_id": 9}, {"request_time": 0, "start_time": 23820, "start_station_id": 12, "end_station_id": 13}, {"request_time": 0, "start_time": 61620, "start_station_id": 4, "end_station_id": 5}, {"request_time": 0, "start_time": 75240, "start_station_id": 9, "end_station_id": 2}, {"request_time": 0, "start_time": 46260, "start_station_id": 12, "end_station_id": 2}, {"request_time": 0, "start_time": 84660, "start_station_id": 8, "end_station_id": 4}, {"request_time": 0, "start_time": 1800, "start_station_id": 6, "end_station_id": 7}, {"request_time": 0, "start_time": 38640, "start_station_id": 9, "end_station_id": 8}, {"request_time": 0, "start_time": 18000, "start_station_id": 1, "end_station_id": 6}, {"request_time": 0, "start_time": 15300, "start_station_id": 9, "end_station_id": 4}, {"request_time": 0, "start_time": 76380, "start_station_id": 5, "end_station_id": 7}, {"request_time": 0, "start_time": 1320, "start_station_id": 4, "end_station_id": 8}, {"request_time": 0, "start_time": 81660, "start_station_id": 9, "end_station_id": 14}, {"request_time": 0, "start_time": 54240, "start_station_id": 6, "end_station_id": 1}, {"request_time": 0, "start_time": 44880, "start_station_id": 10, "end_station_id": 2}, {"request_time": 0, "start_time": 16440, "start_station_id": 4, "end_station_id": 11}, {"request_time": 0, "start_time": 45960, "start_station_id": 9, "end_station_id": 6}, {"request_time": 0, "start_time": 40740, "start_station_id": 8, "end_station_id": 7}, {"request_time": 0, "start_time": 3900, "start_station_id": 10, "end_station_id": 7}, {"request_time": 0, "start_time": 29340, "start_station_id": 3, "end_station_id": 8}, {"request_time": 0, "start_time": 48240, "start_station_id": 1, "end_station_id": 9}, {"request_time": 0, "start_time": 4080, "start_station_id": 12, "end_station_id": 9}, {"request_time": 0, "start_time": 31140, "start_station_id": 9, "end_station_id": 2}, {"request_time": 0, "start_time": 78420, "start_station_id": 9, "end_station_id": 11}, {"request_time": 0, "start_time": 15900, "start_station_id": 14, "end_station_id": 11}, {"request_time": 0, "start_time": 18720, "start_station_id": 9, "end_station_id": 12}, {"request_time": 0, "start_time": 70140, "start_station_id": 11, "end_station_id": 10}, {"request_time": 0, "start_time": 71640, "start_station_id": 13, "end_station_id": 6}, {"request_time": 0, "start_time": 83520, "start_station_id": 10, "end_station_id": 8}, {"request_time": 0, "start_time": 64380, "start_station_id": 9, "end_station_id": 12}, {"request_time": 0, "start_time": 47760, "start_station_id": 4, "end_station_id": 9}, {"request_time": 0, "start_time": 65400, "start_station_id": 10, "end_station_id": 6}, {"request_time": 0, "start_time": 52380, "start_station_id": 6, "end_station_id": 4}, {"request_time": 0, "start_time": 49980, "start_station_id": 9, "end_station_id": 13}, {"request_time": 0, "start_time": 24840, "start_station_id": 6, "end_station_id": 4}, {"request_time": 0, "start_time": 29520, "start_station_id": 13, "end_station_id": 9}, {"request_time": 0, "start_time": 37560, "start_station_id": 13, "end_station_id": 2}, {"request_time": 0, "start_time": 85620, "start_station_id": 9, "end_station_id": 8}, {"request_time": 0, "start_time": 50280, "start_station_id": 9, "end_station_id": 14}, {"request_time": 0, "start_time": 65220, "start_station_id": 2, "end_station_id": 8}, {"request_time": 0, "start_time": 3240, "start_station_id": 0, "end_station_id": 13}, {"request_time": 0, "start_time": 67440, "start_station_id": 9, "end_station_id": 11}, {"request_time": 0, "start_time": 31680, "start_station_id": 11, "end_station_id": 8}, {"request_time": 0, "start_time": 62760, "start_station_id": 13, "end_station_id": 8}, {"request_time": 0, "start_time": 14880, "start_station_id": 7, "end_station_id": 5}, {"request_time": 0, "start_time": 40860, "start_station_id": 5, "end_station_id": 4}, {"request_time": 0, "start_time": 54600, "start_station_id": 5, "end_station_id": 6}, {"request_time": 0, "start_time": 37680, "start_station_id": 9, "end_station_id": 8}, {"request_time": 0, "start_time": 63840, "start_station_id": 10, "end_station_id": 9}, {"request_time": 0, "start_time": 2280, "start_station_id": 6, "end_station_id": 10}, {"request_time": 0, "start_time": 34800, "start_station_id": 5, "end_station_id": 9}, {"request_time": 0, "start_time": 39300, "start_station_id": 8, "end_station_id": 7}, {"request_time": 0, "start_time": 61200, "start_station_id": 9, "end_station_id": 12}, {"request_time": 0, "start_time": 32160, "start_station_id": 4, "end_station_id": 2}, {"request_time": 0, "start_time": 52800, "start_station_id": 13, "end_station_id": 10}, {"request_time": 0, "start_time": 1500, "start_station_id": 0, "end_station_id": 12}, {"request_time": 0, "start_time": 65040, "start_station_id": 4, "end_station_id": 14}, {"request_time": 0, "start_time": 25260, "start_station_id": 14, "end_station_id": 1}, {"request_time": 0, "start_time": 9540, "start_station_id": 7, "end_station_id": 13}, {"request_time": 0, "start_time": 44460, "start_station_id": 0, "end_station_id": 9}, {"request_time": 0, "start_time": 34920, "start_station_id": 5, "end_station_id": 4}, {"request_time": 0, "start_time": 6840, "start_station_id": 0, "end_station_id": 8}, {"request_time": 0, "start_time": 86340, "start_station_id": 13, "end_station_id": 9}, {"request_time": 0, "start_time": 540, "start_station_id": 9, "end_station_id": 0}, {"request_time": 0, "start_time": 66420, "start_station_id": 9, "end_station_id": 7}, {"request_time": 0, "start_time": 24960, "start_station_id": 10, "end_station_id": 9}, {"request_time": 0, "start_time": 29880, "start_station_id": 9, "end_station_id": 10}, {"request_time": 0, "start_time": 43800, "start_station_id": 12, "end_station_id": 1}, {"request_time": 0, "start_time": 24240, "start_station_id": 14, "end_station_id": 7}, {"request_time": 0, "start_time": 7920, "start_station_id": 2, "end_station_id": 8}, {"request_time": 0, "start_time": 55800, "start_station_id": 12, "end_station_id": 8}, {"request_time": 0, "start_time": 37440, "start_station_id": 13, "end_station_id": 10}, {"request_time": 0, "start_time": 57120, "start_station_id": 6, "end_station_id": 9}, {"request_time": 0, "start_time": 79320, "start_station_id": 10, "end_station_id": 8}, {"request_time": 0, "start_time": 12360, "start_station_id": 9, "end_station_id": 12}, {"request_time": 0, "start_time": 14940, "start_station_id": 9, "end_station_id": 13}, {"request_time": 0, "start_time": 37440, "start_station_id": 6, "end_station_id": 7}, {"request_time": 0, "start_time": 3420, "start_station_id": 5, "end_station_id": 1}, {"request_time": 0, "start_time": 12060, "start_station_id": 11, "end_station_id": 9}, {"request_time": 0, "start_time": 25080, "start_station_id": 5, "end_station_id": 9}, {"request_time": 0, "start_time": 5220, "start_station_id": 5, "end_station_id": 9}, {"request_time": 0, "start_time": 30660, "start_station_id": 12, "end_station_id": 7}, {"request_time": 0, "start_time": 6000, "start_station_id": 4, "end_station_id": 9}, {"request_time": 0, "start_time": 23760, "start_station_id": 10, "end_station_id": 0}, {"request_time": 0, "start_time": 64260, "start_station_id": 13, "end_station_id": 2}, {"request_time": 0, "start_time": 46260, "start_station_id": 9, "end_station_id": 2}, {"request_time": 0, "start_time": 81360, "start_station_id": 2, "end_station_id": 4}, {"request_time": 0, "start_time": 5400, "start_station_id": 3, "end_station_id": 9}, {"request_time": 0, "start_time": 59700, "start_station_id": 3, "end_station_id": 0}, {"request_time": 0, "start_time": 77040, "start_station_id": 2, "end_station_id": 3}, {"request_time": 0, "start_time": 61920, "start_station_id": 6, "end_station_id": 9}, {"request_time": 0, "start_time": 54420, "start_station_id": 0, "end_station_id": 13}, {"request_time": 0, "start_time": 36420, "start_station_id": 1, "end_station_id": 8}, {"request_time": 0, "start_time": 29160, "start_station_id": 5, "end_station_id": 2}, {"request_time": 0, "start_time": 83160, "start_station_id": 14, "end_station_id": 11}, {"request_time": 0, "start_time": 40920, "start_station_id": 9, "end_station_id": 6}, {"request_time": 0, "start_time": 48000, "start_station_id": 9, "end_station_id": 2}, {"request_time": 0, "start_time": 85560, "start_station_id": 1, "end_station_id": 9}, {"request_time": 0, "start_time": 66120, "start_station_id": 7, "end_station_id": 6}, {"request_time": 0, "start_time": 7380, "start_station_id": 8, "end_station_id": 12}, {"request_time": 0, "start_time": 8580, "start_station_id": 13, "end_station_id": 12}, {"request_time": 0, "start_time": 28200, "start_station_id": 8, "end_station_id": 10}, {"request_time": 0, "start_time": 13440, "start_station_id": 4, "end_station_id": 9}, {"request_time": 0, "start_time": 74940, "start_station_id": 9, "end_station_id": 11}, {"request_time": 0, "start_time": 38760, "start_station_id": 7, "end_station_id": 12}, {"request_time": 0, "start_time": 47880, "start_station_id": 8, "end_station_id": 5}, {"request_time": 0, "start_time": 41700, "start_station_id": 6, "end_station_id": 9}, {"request_time": 0, "start_time": 11880, "start_station_id": 14, "end_station_id": 6}, {"request_time": 0, "start_time": 78960, "start_station_id": 7, "end_station_id": 6}, {"request_time": 0, "start_time": 52500, "start_station_id": 9, "end_station_id": 2}, {"request_time": 0, "start_time": 37260, "start_station_id": 8, "end_station_id": 12}, {"request_time": 0, "start_time": 6120, "start_station_id": 6, "end_station_id": 1}, {"request_time": 0, "start_time": 2700, "start_station_id": 13, "end_station_id": 9}, {"request_time": 0, "start_time": 26160, "start_station_id": 12, "end_station_id": 10}, {"request_time": 0, "start_time": 19440, "start_station_id": 7, "end_station_id": 4}, {"request_time": 0, "start_time": 26220, "start_station_id": 7, "end_station_id": 5}, {"request_time": 0, "start_time": 28320, "start_station_id": 7, "end_station_id": 6}, {"request_time": 0, "start_time": 36660, "start_station_id": 1, "end_station_id": 2}, {"request_time": 0, "start_time": 40620, "start_station_id": 9, "end_station_id": 2}, {"request_time": 0, "start_time": 9660, "start_station_id": 7, "end_station_id": 5}, {"request_time": 0, "start_time": 6060, "start_station_id": 4, "end_station_id": 7}, {"request_time": 0, "start_time": 55980, "start_station_id": 9, "end_station_id": 8}, {"request_time": 0, "start_time": 8580, "start_station_id": 13, "end_station_id": 14}, {"request_time": 0, "start_time": 39360, "start_station_id": 9, "end_station_id": 3}, {"request_time": 0, "start_time": 46140, "start_station_id": 13, "end_station_id": 5}, {"request_time": 0, "start_time": 39840, "start_station_id": 9, "end_station_id": 12}, {"request_time": 0, "start_time": 71460, "start_station_id": 9, "end_station_id": 10}, {"request_time": 0, "start_time": 43800, "start_station_id": 13, "end_station_id": 9}, {"request_time": 0, "start_time": 31560, "start_station_id": 8, "end_station_id": 6}, {"request_time": 0, "start_time": 60120, "start_station_id": 14, "end_station_id": 13}, {"request_time": 0, "start_time": 71940, "start_station_id": 10, "end_station_id": 6}, {"request_time": 0, "start_time": 27300, "start_station_id": 8, "end_station_id": 11}, {"request_time": 0, "start_time": 82860, "start_station_id": 6, "end_station_id": 13}, {"request_time": 0, "start_time": 3480, "start_station_id": 2, "end_station_id": 9}, {"request_time": 0, "start_time": 60, "start_station_id": 13, "end_station_id": 9}, {"request_time": 0, "start_time": 41940, "start_station_id": 9, "end_station_id": 4}, {"request_time": 0, "start_time": 34380, "start_station_id": 7, "end_station_id": 4}, {"request_time": 0, "start_time": 80580, "start_station_id": 9, "end_station_id": 6}, {"request_time": 0, "start_time": 25800, "start_station_id": 10, "end_station_id": 3}, {"request_time": 0, "start_time": 71460, "start_station_id": 9, "end_station_id": 13}, {"request_time": 0, "start_time": 8940, "start_station_id": 2, "end_station_id": 9}, {"request_time": 0, "start_time": 62040, "start_station_id": 7, "end_station_id": 2}, {"request_time": 0, "start_time": 73740, "start_station_id": 12, "end_station_id": 9}, {"request_time": 0, "start_time": 63300, "start_station_id": 1, "end_station_id": 11}, {"request_time": 0, "start_time": 15540, "start_station_id": 9, "end_station_id": 4}, {"request_time": 0, "start_time": 81660, "start_station_id": 9, "end_station_id": 8}, {"request_time": 0, "start_time": 47760, "start_station_id": 10, "end_station_id": 9}, {"request_time": 0, "start_time": 13320, "start_station_id": 7, "end_station_id": 12}, {"request_time": 0, "start_time": 72240, "start_station_id": 9, "end_station_id": 14}, {"request_time": 0, "start_time": 73620, "start_station_id": 9, "end_station_id": 2}, {"request_time": 0, "start_time": 75300, "start_station_id": 7, "end_station_id": 9}, {"request_time": 0, "start_time": 20340, "start_station_id": 9, "end_station_id": 2}, {"request_time": 0, "start_time": 79440, "start_station_id": 13, "end_station_id": 4}, {"request_time": 0, "start_time": 12660, "start_station_id": 6, "end_station_id": 8}, {"request_time": 0, "start_time": 49560, "start_station_id": 9, "end_station_id": 4}, {"request_time": 0, "start_time": 15720, "start_station_id": 9, "end_station_id": 3}, {"request_time": 0, "start_time": 84180, "start_station_id": 12, "end_station_id": 2}, {"request_time": 0, "start_time": 57660, "start_station_id": 10, "end_station_id": 7}, {"request_time": 0, "start_time": 73800, "start_station_id": 7, "end_station_id": 2}, {"request_time": 0, "start_time": 15900, "start_station_id": 9, "end_station_id": 7}, {"request_time": 0, "start_time": 34560, "start_station_id": 6, "end_station_id": 12}, {"request_time": 0, "start_time": 74640, "start_station_id": 3, "end_station_id": 14}, {"request_time": 0, "start_time": 23280, "start_station_id": 14, "end_station_id": 9}, {"request_time": 0, "start_time": 69240, "start_station_id": 9, "end_station_id": 13}, {"request_time": 0, "start_time": 40560, "start_station_id": 0, "end_station_id": 13}, {"request_time": 0, "start_time": 17220, "start_station_id": 2, "end_station_id": 6}, {"request_time": 0, "start_time": 74640, "start_station_id": 4, "end_station_id": 13}, {"request_time": 0, "start_time": 80880, "start_station_id": 9, "end_station_id": 0}, {"request_time": 0, "start_time": 81420, "start_station_id": 13, "end_station_id": 12}, {"request_time": 0, "start_time": 22320, "start_station_id": 5, "end_station_id": 6}, {"request_time": 0, "start_time": 18420, "start_station_id": 9, "end_station_id": 2}, {"request_time": 0, "start_time": 6720, "start_station_id": 8, "end_station_id": 6}, {"request_time": 0, "start_time": 6960, "start_station_id": 10, "end_station_id": 1}, {"request_time": 0, "start_time": 29580, "start_station_id": 9, "end_station_id": 10}, {"request_time": 0, "start_time": 81180, "start_station_id": 2, "end_station_id": 1}, {"request_time": 0, "start_time": 16980, "start_station_id": 4, "end_station_id": 8}, {"request_time": 0, "start_time": 69720, "start_station_id": 2, "end_station_id": 4}, {"request_time": 0, "start_time": 5040, "start_station_id": 9, "end_station_id": 8}, {"request_time": 0, "start_time": 67620, "start_station_id": 5, "end_station_id": 0}, {"request_time": 0, "start_time": 43320, "start_station_id": 2, "end_station_id": 9}, {"request_time": 0, "start_time": 42780, "start_station_id": 8, "end_station_id": 9}, {"request_time": 0, "start_time": 79020, "start_station_id": 6, "end_station_id": 1}, {"request_time": 0, "start_time": 54120, "start_station_id": 8, "end_station_id": 5}, {"request_time": 0, "start_time": 75240, "start_station_id": 6, "end_station_id": 12}, {"request_time": 0, "start_time": 13200, "start_station_id": 12, "end_station_id": 9}, {"request_time": 0, "start_time": 65220, "start_station_id": 9, "end_station_id": 6}, {"request_time": 0, "start_time": 71040, "start_station_id": 14, "end_station_id": 9}, {"request_time": 0, "start_time": 85740, "start_station_id": 8, "end_station_id": 2}, {"request_time": 0, "start_time": 30900, "start_station_id": 9, "end_station_id": 10}, {"request_time": 0, "start_time": 52260, "start_station_id": 7, "end_station_id": 9}, {"request_time": 0, "start_time": 61200, "start_station_id": 3, "end_station_id": 12}, {"request_time": 0, "start_time": 80040, "start_station_id": 9, "end_station_id": 12}, {"request_time": 0, "start_time": 8820, "start_station_id": 14, "end_station_id": 4}, {"request_time": 0, "start_time": 49620, "start_station_id": 8, "end_station_id": 6}, {"request_time": 0, "start_time": 8460, "start_station_id": 13, "end_station_id": 2}, {"request_time": 0, "start_time": 34980, "start_station_id": 8, "end_station_id": 10}, {"request_time": 0, "start_time": 81060, "start_station_id": 11, "end_station_id": 12}, {"request_time": 0, "start_time": 62940, "start_station_id": 11, "end_station_id": 8}, {"request_time": 0, "start_time": 46260, "start_station_id": 13, "end_station_id": 10}, {"request_time": 0, "start_time": 59880, "start_station_id": 5, "end_station_id": 9}, {"request_time": 0, "start_time": 22860, "start_station_id": 10, "end_station_id": 1}, {"request_time": 0, "start_time": 13140, "start_station_id": 4, "end_station_id": 6}, {"request_time": 0, "start_time": 55380, "start_station_id": 9, "end_station_id": 14}, {"request_time": 0, "start_time": 73020, "start_station_id": 4, "end_station_id": 6}, {"request_time": 0, "start_time": 60540, "start_station_id": 4, "end_station_id": 0}, {"request_time": 0, "start_time": 77280, "start_station_id": 8, "end_station_id": 9}, {"request_time": 0, "start_time": 78300, "start_station_id": 5, "end_station_id": 2}, {"request_time": 0, "start_time": 77760, "start_station_id": 6, "end_station_id": 9}, {"request_time": 0, "start_time": 53820, "start_station_id": 5, "end_station_id": 12}, {"request_time": 0, "start_time": 77640, "start_station_id": 13, "end_station_id": 6}, {"request_time": 0, "start_time": 75600, "start_station_id": 10, "end_station_id": 8}, {"request_time": 0, "start_time": 60120, "start_station_id": 13, "end_station_id": 6}, {"request_time": 0, "start_time": 60360, "start_station_id": 13, "end_station_id": 9}, {"request_time": 0, "start_time": 73080, "start_station_id": 12, "end_station_id": 13}, {"request_time": 0, "start_time": 6900, "start_station_id": 6, "end_station_id": 8}, {"request_time": 0, "start_time": 67380, "start_station_id": 11, "end_station_id": 9}, {"request_time": 0, "start_time": 71580, "start_station_id": 4, "end_station_id": 2}, {"request_time": 0, "start_time": 62220, "start_station_id": 1, "end_station_id": 7}, {"request_time": 0, "start_time": 75240, "start_station_id": 10, "end_station_id": 9}, {"request_time": 0, "start_time": 63600, "start_station_id": 9, "end_station_id": 1}, {"request_time": 0, "start_time": 45000, "start_station_id": 6, "end_station_id": 0}, {"request_time": 0, "start_time": 51600, "start_station_id": 10, "end_station_id": 9}, {"request_time": 0, "start_time": 40200, "start_station_id": 12, "end_station_id": 13}, {"request_time": 0, "start_time": 30000, "start_station_id": 4, "end_station_id": 5}, {"request_time": 0, "start_time": 9300, "start_station_id": 9, "end_station_id": 2}, {"request_time": 0, "start_time": 58320, "start_station_id": 12, "end_station_id": 2}, {"request_time": 0, "start_time": 66060, "start_station_id": 8, "end_station_id": 4}, {"request_time": 0, "start_time": 32520, "start_station_id": 6, "end_station_id": 7}, {"request_time": 0, "start_time": 24960, "start_station_id": 9, "end_station_id": 8}, {"request_time": 0, "start_time": 45300, "start_station_id": 1, "end_station_id": 6}, {"request_time": 0, "start_time": 7380, "start_station_id": 9, "end_station_id": 4}, {"request_time": 0, "start_time": 12120, "start_station_id": 5, "end_station_id": 7}, {"request_time": 0, "start_time": 28320, "start_station_id": 4, "end_station_id": 8}, {"request_time": 0, "start_time": 9840, "start_station_id": 9, "end_station_id": 14}, {"request_time": 0, "start_time": 4620, "start_station_id": 6, "end_station_id": 1}, {"request_time": 0, "start_time": 82560, "start_station_id": 10, "end_station_id": 2}, {"request_time": 0, "start_time": 84420, "start_station_id": 4, "end_station_id": 11}, {"request_time": 0, "start_time": 7440, "start_station_id": 9, "end_station_id": 6}, {"request_time": 0, "start_time": 53580, "start_station_id": 8, "end_station_id": 7}, {"request_time": 0, "start_time": 7500, "start_station_id": 10, "end_station_id": 7}, {"request_time": 0, "start_time": 47820, "start_station_id": 3, "end_station_id": 8}, {"request_time": 0, "start_time": 19560, "start_station_id": 1, "end_station_id": 9}, {"request_time": 0, "start_time": 41520, "start_station_id": 12, "end_station_id": 9}, {"request_time": 0, "start_time": 54180, "start_station_id": 9, "end_station_id": 2}, {"request_time": 0, "start_time": 81480, "start_station_id": 9, "end_station_id": 11}, {"request_time": 0, "start_time": 22320, "start_station_id": 14, "end_station_id": 11}, {"request_time": 0, "start_time": 24540, "start_station_id": 9, "end_station_id": 12}, {"request_time": 0, "start_time": 60840, "start_station_id": 11, "end_station_id": 10}, {"request_time": 0, "start_time": 39060, "start_station_id": 13, "end_station_id": 6}, {"request_time": 0, "start_time": 18840, "start_station_id": 10, "end_station_id": 8}, {"request_time": 0, "start_time": 70380, "start_station_id": 9, "end_station_id": 12}, {"request_time": 0, "start_time": 62460, "start_station_id": 4, "end_station_id": 9}, {"request_time": 0, "start_time": 21600, "start_station_id": 10, "end_station_id": 6}, {"request_time": 0, "start_time": 49200, "start_station_id": 6, "end_station_id": 4}, {"request_time": 0, "start_time": 62160, "start_station_id": 9, "end_station_id": 13}, {"request_time": 0, "start_time": 44400, "start_station_id": 6, "end_station_id": 4}, {"request_time": 0, "start_time": 39000, "start_station_id": 13, "end_station_id": 9}, {"request_time": 0, "start_time": 78480, "start_station_id": 13, "end_station_id": 2}, {"request_time": 0, "start_time": 31980, "start_station_id": 9, "end_station_id": 8}, {"request_time": 0, "start_time": 51360, "start_station_id": 9, "end_station_id": 14}, {"request_time": 0, "start_time": 81120, "start_station_id": 2, "end_station_id": 8}, {"request_time": 0, "start_time": 32820, "start_station_id": 0, "end_station_id": 13}, {"request_time": 0, "start_time": 40020, "start_station_id": 9, "end_station_id": 11}, {"request_time": 0, "start_time": 10500, "start_station_id": 11, "end_station_id": 8}, {"request_time": 0, "start_time": 81660, "start_station_id": 13, "end_station_id": 8}, {"request_time": 0, "start_time": 83580, "start_station_id": 7, "end_station_id": 5}, {"request_time": 0, "start_time": 45720, "start_station_id": 5, "end_station_id": 4}, {"request_time": 0, "start_time": 80340, "start_station_id": 5, "end_station_id": 6}, {"request_time": 0, "start_time": 61020, "start_station_id": 9, "end_station_id": 8}, {"request_time": 0, "start_time": 36780, "start_station_id": 10, "end_station_id": 9}, {"request_time": 0, "start_time": 75900, "start_station_id": 6, "end_station_id": 10}, {"request_time": 0, "start_time": 4980, "start_station_id": 5, "end_station_id": 9}, {"request_time": 0, "start_time": 77520, "start_station_id": 8, "end_station_id": 7}, {"request_time": 0, "start_time": 72120, "start_station_id": 9, "end_station_id": 12}, {"request_time": 0, "start_time": 85380, "start_station_id": 4, "end_station_id": 2}, {"request_time": 0, "start_time": 32400, "start_station_id": 13, "end_station_id": 10}, {"request_time": 0, "start_time": 32100, "start_station_id": 0, "end_station_id": 12}, {"request_time": 0, "start_time": 54780, "start_station_id": 4, "end_station_id": 14}, {"request_time": 0, "start_time": 18420, "start_station_id": 14, "end_station_id": 1}, {"request_time": 0, "start_time": 14820, "start_station_id": 7, "end_station_id": 13}, {"request_time": 0, "start_time": 11340, "start_station_id": 0, "end_station_id": 9}, {"request_time": 0, "start_time": 51240, "start_station_id": 5, "end_station_id": 4}, {"request_time": 0, "start_time": 37200, "start_station_id": 0, "end_station_id": 8}, {"request_time": 0, "start_time": 19200, "start_station_id": 13, "end_station_id": 9}, {"request_time": 0, "start_time": 38400, "start_station_id": 9, "end_station_id": 0}, {"request_time": 0, "start_time": 66480, "start_station_id": 9, "end_station_id": 7}, {"request_time": 0, "start_time": 49680, "start_station_id": 10, "end_station_id": 9}, {"request_time": 0, "start_time": 64740, "start_station_id": 9, "end_station_id": 10}, {"request_time": 0, "start_time": 69960, "start_station_id": 12, "end_station_id": 1}, {"request_time": 0, "start_time": 26520, "start_station_id": 14, "end_station_id": 7}, {"request_time": 0, "start_time": 63540, "start_station_id": 2, "end_station_id": 8}, {"request_time": 0, "start_time": 55740, "start_station_id": 12, "end_station_id": 8}, {"request_time": 0, "start_time": 13740, "start_station_id": 13, "end_station_id": 10}, {"request_time": 0, "start_time": 32580, "start_station_id": 6, "end_station_id": 9}, {"request_time": 0, "start_time": 29700, "start_station_id": 10, "end_station_id": 8}, {"request_time": 0, "start_time": 78240, "start_station_id": 9, "end_station_id": 12}, {"request_time": 0, "start_time": 33720, "start_station_id": 9, "end_station_id": 13}, {"request_time": 0, "start_time": 69300, "start_station_id": 6, "end_station_id": 7}, {"request_time": 0, "start_time": 22080, "start_station_id": 5, "end_station_id": 1}, {"request_time": 0, "start_time": 47340, "start_station_id": 11, "end_station_id": 9}, {"request_time": 0, "start_time": 3720, "start_station_id": 5, "end_station_id": 9}, {"request_time": 0, "start_time": 28020, "start_station_id": 5, "end_station_id": 9}, {"request_time": 0, "start_time": 51000, "start_station_id": 12, "end_station_id": 7}, {"request_time": 0, "start_time": 84060, "start_station_id": 4, "end_station_id": 9}, {"request_time": 0, "start_time": 49080, "start_station_id": 10, "end_station_id": 0}, {"request_time": 0, "start_time": 74400, "start_station_id": 13, "end_station_id": 2}, {"request_time": 0, "start_time": 37740, "start_station_id": 9, "end_station_id": 2}, {"request_time": 0, "start_time": 15720, "start_station_id": 2, "end_station_id": 4}, {"request_time": 0, "start_time": 31080, "start_station_id": 3, "end_station_id": 9}, {"request_time": 0, "start_time": 33240, "start_station_id": 3, "end_station_id": 0}, {"request_time": 0, "start_time": 74820, "start_station_id": 2, "end_station_id": 3}, {"request_time": 0, "start_time": 42000, "start_station_id": 6, "end_station_id": 9}, {"request_time": 0, "start_time": 74820, "start_station_id": 0, "end_station_id": 13}, {"request_time": 0, "start_time": 14940, "start_station_id": 1, "end_station_id": 8}, {"request_time": 0, "start_time": 20640, "start_station_id": 5, "end_station_id": 2}, {"request_time": 0, "start_time": 75900, "start_station_id": 14, "end_station_id": 11}, {"request_time": 0, "start_time": 30120, "start_station_id": 9, "end_station_id": 6}, {"request_time": 0, "start_time": 41280, "start_station_id": 9, "end_station_id": 2}, {"request_time": 0, "start_time": 83160, "start_station_id": 1, "end_station_id": 9}, {"request_time": 0, "start_time": 39540, "start_station_id": 7, "end_station_id": 6}, {"request_time": 0, "start_time": 78540, "start_station_id": 8, "end_station_id": 12}, {"request_time": 0, "start_time": 74700, "start_station_id": 13, "end_station_id": 12}, {"request_time": 0, "start_time": 11040, "start_station_id": 8, "end_station_id": 10}, {"request_time": 0, "start_time": 80280, "start_station_id": 4, "end_station_id": 9}, {"request_time": 0, "start_time": 77520, "start_station_id": 9, "end_station_id": 11}, {"request_time": 0, "start_time": 22740, "start_station_id": 7, "end_station_id": 12}, {"request_time": 0, "start_time": 17460, "start_station_id": 8, "end_station_id": 5}, {"request_time": 0, "start_time": 56880, "start_station_id": 6, "end_station_id": 9}, {"request_time": 0, "start_time": 45660, "start_station_id": 14, "end_station_id": 6}, {"request_time": 0, "start_time": 14580, "start_station_id": 7, "end_station_id": 6}, {"request_time": 0, "start_time": 4980, "start_station_id": 9, "end_station_id": 2}, {"request_time": 0, "start_time": 9900, "start_station_id": 8, "end_station_id": 12}, {"request_time": 0, "start_time": 14580, "start_station_id": 6, "end_station_id": 1}, {"request_time": 0, "start_time": 85260, "start_station_id": 13, "end_station_id": 9}, {"request_time": 0, "start_time": 81720, "start_station_id": 12, "end_station_id": 10}, {"request_time": 0, "start_time": 58680, "start_station_id": 7, "end_station_id": 4}, {"request_time": 0, "start_time": 48420, "start_station_id": 7, "end_station_id": 5}, {"request_time": 0, "start_time": 13020, "start_station_id": 7, "end_station_id": 6}, {"request_time": 0, "start_time": 43020, "start_station_id": 1, "end_station_id": 2}, {"request_time": 0, "start_time": 46860, "start_station_id": 9, "end_station_id": 2}, {"request_time": 0, "start_time": 62040, "start_station_id": 7, "end_station_id": 5}, {"request_time": 0, "start_time": 35340, "start_station_id": 4, "end_station_id": 7}, {"request_time": 0, "start_time": 77940, "start_station_id": 9, "end_station_id": 8}, {"request_time": 0, "start_time": 26220, "start_station_id": 13, "end_station_id": 14}, {"request_time": 0, "start_time": 70200, "start_station_id": 9, "end_station_id": 3}, {"request_time": 0, "start_time": 36060, "start_station_id": 13, "end_station_id": 5}, {"request_time": 0, "start_time": 78780, "start_station_id": 9, "end_station_id": 12}, {"request_time": 0, "start_time": 82560, "start_station_id": 9, "end_station_id": 10}, {"request_time": 0, "start_time": 17940, "start_station_id": 13, "end_station_id": 9}, {"request_time": 0, "start_time": 82200, "start_station_id": 8, "end_station_id": 6}, {"request_time": 0, "start_time": 46860, "start_station_id": 14, "end_station_id": 13}, {"request_time": 0, "start_time": 72060, "start_station_id": 10, "end_station_id": 6}, {"request_time": 0, "start_time": 86220, "start_station_id": 8, "end_station_id": 11}, {"request_time": 0, "start_time": 35220, "start_station_id": 6, "end_station_id": 13}, {"request_time": 0, "start_time": 32940, "start_station_id": 2, "end_station_id": 9}, {"request_time": 0, "start_time": 74160, "start_station_id": 13, "end_station_id": 9}, {"request_time": 0, "start_time": 46200, "start_station_id": 9, "end_station_id": 4}, {"request_time": 0, "start_time": 69540, "start_station_id": 7, "end_station_id": 4}, {"request_time": 0, "start_time": 48900, "start_station_id": 9, "end_station_id": 6}, {"request_time": 0, "start_time": 42000, "start_station_id": 10, "end_station_id": 3}, {"request_time": 0, "start_time": 40980, "start_station_id": 9, "end_station_id": 13}, {"request_time": 0, "start_time": 41280, "start_station_id": 2, "end_station_id": 9}, {"request_time": 0, "start_time": 25260, "start_station_id": 7, "end_station_id": 2}, {"request_time": 0, "start_time": 86160, "start_station_id": 12, "end_station_id": 9}, {"request_time": 0, "start_time": 9960, "start_station_id": 1, "end_station_id": 11}, {"request_time": 0, "start_time": 23280, "start_station_id": 9, "end_station_id": 4}, {"request_time": 0, "start_time": 8700, "start_station_id": 9, "end_station_id": 8}, {"request_time": 0, "start_time": 24720, "start_station_id": 10, "end_station_id": 9}, {"request_time": 0, "start_time": 61380, "start_station_id": 7, "end_station_id": 12}, {"request_time": 0, "start_time": 83880, "start_station_id": 9, "end_station_id": 14}, {"request_time": 0, "start_time": 75780, "start_station_id": 9, "end_station_id": 2}, {"request_time": 0, "start_time": 32640, "start_station_id": 7, "end_station_id": 9}, {"request_time": 0, "start_time": 33120, "start_station_id": 9, "end_station_id": 2}, {"request_time": 0, "start_time": 72720, "start_station_id": 13, "end_station_id": 4}, {"request_time": 0, "start_time": 26520, "start_station_id": 6, "end_station_id": 8}, {"request_time": 0, "start_time": 81180, "start_station_id": 9, "end_station_id": 4}, {"request_time": 0, "start_time": 1380, "start_station_id": 9, "end_station_id": 3}, {"request_time": 0, "start_time": 63960, "start_station_id": 12, "end_station_id": 2}, {"request_time": 0, "start_time": 60840, "start_station_id": 10, "end_station_id": 7}, {"request_time": 0, "start_time": 50880, "start_station_id": 7, "end_station_id": 2}, {"request_time": 0, "start_time": 54060, "start_station_id": 9, "end_station_id": 7}, {"request_time": 0, "start_time": 57660, "start_station_id": 6, "end_station_id": 12}, {"request_time": 0, "start_time": 3780, "start_station_id": 3, "end_station_id": 14}, {"request_time": 0, "start_time": 8220, "start_station_id": 14, "end_station_id": 9}, {"request_time": 0, "start_time": 82800, "start_station_id": 9, "end_station_id": 13}, {"request_time": 0, "start_time": 62940, "start_station_id": 0, "end_station_id": 13}, {"request_time": 0, "start_time": 45840, "start_station_id": 2, "end_station_id": 6}, {"request_time": 0, "start_time": 82020, "start_station_id": 4, "end_station_id": 13}, {"request_time": 0, "start_time": 78600, "start_station_id": 9, "end_station_id": 0}, {"request_time": 0, "start_time": 82260, "start_station_id": 13, "end_station_id": 12}, {"request_time": 0, "start_time": 41520, "start_station_id": 5, "end_station_id": 6}, {"request_time": 0, "start_time": 68460, "start_station_id": 9, "end_station_id": 2}, {"request_time": 0, "start_time": 15720, "start_station_id": 8, "end_station_id": 6}, {"request_time": 0, "start_time": 81600, "start_station_id": 10, "end_station_id": 1}, {"request_time": 0, "start_time": 56160, "start_station_id": 9, "end_station_id": 10}, {"request_time": 0, "start_time": 66360, "start_station_id": 2, "end_station_id": 1}, {"request_time": 0, "start_time": 30480, "start_station_id": 4, "end_station_id": 8}, {"request_time": 0, "start_time": 37920, "start_station_id": 2, "end_station_id": 4}, {"request_time": 0, "start_time": 6060, "start_station_id": 9, "end_station_id": 8}, {"request_time": 0, "start_time": 17760, "start_station_id": 5, "end_station_id": 0}, {"request_time": 0, "start_time": 32400, "start_station_id": 2, "end_station_id": 9}, {"request_time": 0, "start_time": 59340, "start_station_id": 8, "end_station_id": 9}, {"request_time": 0, "start_time": 29700, "start_station_id": 6, "end_station_id": 1}, {"request_time": 0, "start_time": 65040, "start_station_id": 8, "end_station_id": 5}, {"request_time": 0, "start_time": 9480, "start_station_id": 6, "end_station_id": 12}, {"request_time": 0, "start_time": 23820, "start_station_id": 12, "end_station_id": 9}, {"request_time": 0, "start_time": 56040, "start_station_id": 9, "end_station_id": 6}, {"request_time": 0, "start_time": 16740, "start_station_id": 14, "end_station_id": 9}, {"request_time": 0, "start_time": 42540, "start_station_id": 8, "end_station_id": 2}, {"request_time": 0, "start_time": 60180, "start_station_id": 9, "end_station_id": 10}, {"request_time": 0, "start_time": 76020, "start_station_id": 7, "end_station_id": 9}, {"request_time": 0, "start_time": 16560, "start_station_id": 3, "end_station_id": 12}, {"request_time": 0, "start_time": 73080, "start_station_id": 9, "end_station_id": 12}, {"request_time": 0, "start_time": 60, "start_station_id": 14, "end_station_id": 4}, {"request_time": 0, "start_time": 50640, "start_station_id": 8, "end_station_id": 6}]}